Workbook

Sheet Runwal
C1: Runwal - Subodh | D1: Sobha
A2: Ambedkar Nagar, Worli | C2: i | D2: S | E2: p1
A3: Borla | D3: ☑
A4: Jasmine (JV/JD) | C4: x | E4: p3
A5: Khajuria Nagar | C5: o
A6: New Jal Darshan | C6: i | D6: S | E6: p2
A7: Nityanand Baug | C7: x | D7: o | E7: p3
A8: Prahlad CHSL - Santacurz | D8: o
A9: Rajendra Park & Nalanda Mall, Goregaon (West) | C9: o | E9: p3
A10: Sumer Nagar | C10: o | D10: o
A11: Tolaram | C11: i | D11: o | E11: p1
A12: Redstone, Juhu | C12: x
A13: Maker Mahal | C13: i | E13: P2
A16: Runwal Enterprises
A17: Property Name | B17: Amit jis Comment | C17: IM | D17: Location | E17: Deal Type | F17: Plot size (sq.m.) | G17: Topline (in Crores) | H17: Comment | I17: Status | J17: Lastest updated
A18: LIC Colony | B18: Interested - Get offer | C18: Send Feasibility for Offer | D18: Mulund | E18: Redevelopment | F18: 10715 | G18: 847 | H18: New Opportunity, Anex appointed as Representatives for the society | I18: New | J18: Society is actively looking to get redeveloped
A19: Manish Nagar | D19: =VLOOKUP(A19,'Opps combined list'!$C$4:$E$42,2,FALSE) -> Andheri West | E19: Society Redevelopment | F19: 10217 | G19: 1270 | H19: New Opportunity, Anex appointed as PMC for society | I19: New | J19: Society is actively looking to get redeveloped
A20: Karnatak | D20: Mahim West | E20: Society Redevelopment | F20: 5850 | G20: 852 | H20: New Opportunity, Anex pursuing appointed as PMC for society | I20: New
A21: Sea Glimpse | D21: Worli | E21: Society Redevelopment | F21: 1696 | G21: 450 | H21: New Opportunity | I21: New | J21: Society is actively looking to get redeveloped
A22: Ambedkar Nagar, Worli | D22: Worli | E22: Society Redevelopment | F22: 9311 | G22: 1481 | H22: The Group has shown interest in the opportunity, Mahesh sir has also conducted a site with Team Anex. EoI format shared | I22: Interested (P1) | J22: Society has one offer, they believe they should get a better offer and looking for potential developers
A23: Tolaram | D23: =VLOOKUP(A23,'Opps combined list'!$C$4:$E$42,2,FALSE) -> Chembur | E23: Society Redevelopment | F23: 18618 | G23: 2000 | H23: The Group has shown interest in the opportunity, Mahesh sir raised his concerns over access and buildibilty | I23: Interested (P1) | J23: Society is actively looking developers, open to one on one dealing
A24: New Jal Darshan | D24: Bandra West | E24: Society Redevelopment | F24: 2053.2 | G24: 290 | H24: The Group has shown interest in the opportunity, and will participate in the Tender | I24: Interested (P2) | J24: Private tender will be floated soon
A25: Maker Mahal | D25: =VLOOKUP(A25,'Opps combined list'!$C$4:$E$42,2,FALSE) -> Bandra West | E25: Outright | F25: 2025.9 | G25: 800 | H25: Liked the location, Mahesh sir, showed hesistance due to high outright value | I25: Interested (P2) | J25: Last offer from Mahindra at 235 cr. is being evaluated
A26: Jasmine (JV/JD) | D26: Colaba | E26: JV/JD | F26: 1270.91 | G26: 336 | H26: Mahesh sir wanted more clarity on Development for Heritage structures. Also plot size small | I26: Interested (P3) | J26: Landowner is actively looking for a partner
A27: Sumer Nagar | B27: Interested | D27: =VLOOKUP(A27,'Opps combined list'!$C$4:$E$42,2,FALSE) -> Borivali | E27: Redevelopment | F27: 12662 | G27: 1330 | H27: Shared with the group, they are evaluating | I27: Interested | J27: Society is actively looking to appoint Anex as their PMC
A28: Khajuria Nagar | B28: Interested - Get offer | C28: Send Feasibility for Offer | D28: Kandivali West | E28: Redevelopment | F28: 11895.33 | G28: 1200 | H28: Location Mentioned to Mahesh as slow cooking when we meet him, he was interested Prima facie | I28: Interested | J28: Society is actively looking for developers, open to one on one dealing
A29: Lokhandwala | D29: Versova | E29: Society Redevelopment | F29: - | G29: - | H29: Part of our initial discussions, the group has shown interest | I29: Slowing cooking | J29: Society is actively looking to appoint a PMC
A30: Nityanand Baug | D30: Chembr | E30: JV/JD | F30: 15348 | G30: 1650 | H30: Mahesh sir was not very Keen due to its history | I30: Dropped | J30: Society is actively looking to appoint a PMC
A31: Rajendra Park | B31: Dropped | D31: Goregoan West | E31: JV/JD | F31: 6777.82 | G31: 780 | H31: Mahesh sir was not very Keen due to its topline being small | I31: Dropped | J31: Existing developer is actively looking for a new partner
A32: Shivam Complex | B32: Dropped | D32: Vashi | E32: JV/JD | F32: 3493.5
A33: Dharavi SRA | B33: Dropped | D33: Dharavi | E33: JV/JD | F33: 5107
A34: SWAN | B34: Interested | D34: Sewri | E34: Outright | F34: 2521
A35: GTB | B35: Amit ji to discuss with SR | C35: Share IM | D35: GTB nagar | E35: JV/JD | F35: 20681.32
A36: Mulund - Transcon | B36: Dropped | D36: Mulund West | E36: JV/JD | F36: 80000
A37: Girgaum | B37: Interested | C37: Share IM | D37: Girgaon | E37: JV/JD | F37: 4605.38
A38: Diwan | B38: Dropped | D38: Marol | E38: Outright | F38: 8743
A39: Shedung | B39: Dropped | D39: Panvel | E39: Outright | F39: =18*4046 -> 72828
A40: Tolaram | B40: Interested | C40: Share IM | D40: Chembur | E40: Redevelopment | F40: 18618
A41: MTNL - 1 acre | B41: Interested | C41: Share IM | D41: Malad west | E41: Outright | F41: 4000
A42: Wise City | B42: Interested | C42: Prep | D42: Panvel | E42: Outright | F42: X
A43: Sarvodhaya Nagar | B43: Interested | C43: Share IM | D43: Mulund West | E43: Redevelopment | F43: 10429
A44: Navi Mumbai - opp IBIS hotel | B44: Interested | C44: Prep | D44: Navi Mumbai | E44: JV/JD | F44: 35410

Sheet < 1,000 Sq.m. 
B4: Property | C4: Location | D4: Rescource | E4: Status | F4: SPOC / Agent | G4: Type | H4: Location | I4: Plot Size (sq.m.) | J4: FSI Potential | K4: Regulation Proposed | L4: Outright Price (INR)
A5: 1 | B5: Shishir | C5: Juhu | D5: Vru | E5: To be figured | F5: Duke | G5: Outright | H5: Maps | I5: 537 | J5: 5.4 | K5: 33(20B)
A6: 2 | B6: VIP | C6: Vile Parle East | D6: Vineet | E6: Cold | G6: Outright | H6: Maps | I6: 909.2 | J6: 3.04 | K6: 30(A) + 20(B) | L6: 27 Cr.
A7: 3 | B7: Plot next to Morumal Mansion CHSL | C7: Khar West | D7: SP | E7: Cold | F7: Dinesh | G7: Outright | H7: Maps | I7: 915 | J7: 5.4
A8: 4 | B8: Vijay Bharat | C8: andheri west | D8: SP | E8: To be revived | F8: Sachinji Solanki | G8: Outright | H8: Maps | I8: 1024 | J8: 5.4 | K8: 30(A)+20(B)
A9: 5 | B9: NS Juhu | C9: Juhu | F9: Hardik | G9: Outright | H9: Maps | I9: 829 | K9: FF not prepared | L9: 110 Cr.
A10: 6 | B10: Gitanjali CHS | C10: Santacruz East | E10: FF pending | F10: Pritesh Desai | G10: Outright | H10: Maps | I10: 1063 | K10: FF not prepared | L10: 50 Cr.
A11: 7 | B11: Sherly | C11: Bandra West | E11: FF pending | F11: Varun | G11: Outright | H11: Maps | I11: 412 | K11: FF not prepared | L11: 30 Cr.
A12: 8 | B12: Malti Mahal | G12: Outright | H12: Maps | I12: 568 | K12: FF not prepared | L12: 40 Cr.
A13: 9 | B13: Kothari Niwas | G13: Outright | H13: Maps | I13: 1711
A14: 10 | B14: Moray House | G14: Outright | H14: Maps | I14: 835 | L14: 75 Cr.
A15: 11 | B15: Redstone | G15: Outright | H15: Maps | I15: 814 | L15: 95 Cr.

Sheet Data Dump
B4: Propetry | C4: Location | D4: Handover | E4: Rescource | G4: Status | H4: SPOC / Agent | I4: Type 3 | J4: Location | K4: Plot size (sq.m.) | L4: FSI Potential | M4: Regulation Proposed | N4: Development Potential (sq.m.) | O4: Rehab Area (sq.m.) | P4: Sale Area (sq.m.) | Q4: Sale Rate Considered (psf) | R4: Initial Investment | S4: Profit | T4: Topline (in Crores) | U4: Next Step | V4: Latest update (Top to bottom) | W4: Click Up | X4: Excel
A5: 1 | B5: New Hindustan CHS | C5: Bandra W | G5: Dropped | H5: Sameer Sata | I5: Redevelopment | R5: =INDEX('Opps combined list'!$1:$1048576,MATCH('Data Dump'!$B48,'Opps combined list'!$C:$C,0),MATCH('Data Dump'!R$4,'Opps combined list'!$4:$4,0)) -> #N/A | S5: =INDEX('Opps combined list'!$1:$1048576,MATCH('Data Dump'!$B48,'Opps combined list'!$C:$C,0),MATCH('Data Dump'!S$4,'Opps combined list'!$4:$4,0)) -> #N/A | U5: Follow up | V5: Meeting done with Kishore Gala at Circuit City, to understand next steps / PMC appointment
A6: 2 | B6: Northern India CHSL | C6: Wadala | G6: Dropped | H6: Parimal Parekh | I6: Redevelopment | R6: =INDEX('Opps combined list'!$1:$1048576,MATCH('Data Dump'!$B123,'Opps combined list'!$C:$C,0),MATCH('Data Dump'!R$4,'Opps combined list'!$4:$4,0)) -> #N/A | S6: =INDEX('Opps combined list'!$1:$1048576,MATCH('Data Dump'!$B123,'Opps combined list'!$C:$C,0),MATCH('Data Dump'!S$4,'Opps combined list'!$4:$4,0)) -> #N/A | U6: Slow cooking | V6: -Meeting done, legal procedure being explained -To meet society and understand next steps prepare IM and Feasibility. Meeting scheduled for 13/10 @10:30 Am - Presentation to be prepared (Legal Note + Individual vs Cluster Pros & Cons)
A7: 3 | B7: Uttrayan CHS | C7: Andheri E | G7: Dropped | H7: AOS | I7: Redevelopment | R7: =INDEX('Opps combined list'!$1:$1048576,MATCH('Data Dump'!$B141,'Opps combined list'!$C:$C,0),MATCH('Data Dump'!R$4,'Opps combined list'!$4:$4,0)) -> #N/A | S7: =INDEX('Opps combined list'!$1:$1048576,MATCH('Data Dump'!$B141,'Opps combined list'!$C:$C,0),MATCH('Data Dump'!S$4,'Opps combined list'!$4:$4,0)) -> #N/A | U7: wait | V7: EOI sent - With society for consideration
A8: 4 | B8: Virwani CHSL | C8: Goregaon E | G8: Dropped | H8: AG | I8: Redevelopment | R8: =INDEX('Opps combined list'!$1:$1048576,MATCH('Data Dump'!#REF!,'Opps combined list'!$C:$C,0),MATCH('Data Dump'!R$4,'Opps combined list'!$4:$4,0)) -> #REF! | S8: =INDEX('Opps combined list'!$1:$1048576,MATCH('Data Dump'!#REF!,'Opps combined list'!$C:$C,0),MATCH('Data Dump'!S$4,'Opps combined list'!$4:$4,0)) -> #REF! | V8: -On Hold from Virvani's side -Sunteck has submitted an offer, to follow up with PMC. Sunteck revised offer pending
A9: 5 | B9: Gokul Regency one | C9: 0 | G9: Dropped | H9: 0 | I9: Redevelopment | V9: 0
A10: 6 | B10: Khandke Cluster | C10: Dadar W | G10: Dropped | H10: Mahendra Kasture | I10: Redevelopment | V10: Awaiting technical feasibility from the architect, MK to provide
A11: 7 | B11: Kitan apartments | C11: Matunga East | G11: Dropped | H11: BL Pandey | I11: Redevelopment | V11: 0
A12: 8 | B12: Land Breeze, Pali hill | C12: Bandra | G12: Dropped | H12: Prem/Sachin | I12: Redevelopment | V12: -Meet with Society. They want to get rid of current PMC
A13: 9 | B13: Lloyds Society | C13: Prabhadevi | G13: Dropped | H13: VKG | I13: Redevelopment | V13: Not lucrative - No action to be taken for VKG
A14: 10 | B14: Mangal Orchid | C14: Versova | G14: Dropped | H14: AOS | I14: Redevelopment | V14: Kuwadekar appointed
A15: 11 | B15: Neelkanth | C15: Matunga West | G15: Dropped | H15: Sachin Agrawal | I15: Redevelopment | U15: Follow up with Sachin
A16: 12 | B16: One Universe | C16: Oshiwara | G16: Dropped | H16: Ashok Kothari | I16: Redevelopment | K16: 0 | V16: - not feasibile -Study feasibility and understand development potential for further action. AG to get back on 08/10 | W16: Updated | X16: Updated
A17: 13 | B17: Orbit Ventures | C17: Lower Parel | G17: Dropped | H17: Vinita CBRE | I17: Redevelopment | K17: 0 | V17: To understand next steps
A18: 14 | B18: Parijat (Tender) | C18: 0 | G18: Dropped | H18: 0 | I18: Redevelopment | K18: 0 | V18: 0
A19: 15 | B19: Poonam Nagar MHADA | C19: Jogeshwari East | G19: Dropped | H19: 0 | I19: Redevelopment | K19: 0 | V19: -Dropped, not feasibile
A20: 16 | B20: Prathamesh CHS | C20: Andheri W | G20: Dropped | H20: Mr. Arvind Pahwa | I20: Redevelopment | K20: 0 | V20: - 5-6 buildings - background check then make inroads through SPOC
A21: 17 | B21: Raji Commercial Complex | C21: 0 | G21: Dropped | H21: 0 | I21: Redevelopment | K21: 0 | V21: 0
A22: 18 | B22: Sadguru | C22: Ghatkopar | G22: Dropped | H22: Agrawal | I22: Redevelopment | K22: 0 | V22: 0
A23: 19 | B23: Sai Ashish | C23: Mulund W | G23: Dropped | H23: Ashok Borana | I23: Redevelopment | K23: 0 | V23: Update to be taken for PMC Apppointment
A24: 20 | B24: Sandom Chawl | C24: Vile Parle | G24: Dropped | H24: Mahendra Kasture | I24: Redevelopment | K24: 0 | V24: - Land owner wants 60cr -JV Proposal - Queries with CTS, Development - Share with Veena,VKG, Vineet's uncle only IM (challenges (Metro Influence))
A25: 21 | B25: Shahid Bhagatsingh Nagar | C25: Bandra East | G25: Dropped | H25: 0 | I25: Redevelopment | K25: 0 | V25: -Update from Makwana needed
A26: 22 | B26: Shivdham | C26: Chembur | G26: Dropped | H26: Ashok Borana | I26: Redevelopment | K26: 0 | V26: Understand the status of appointing us as PMC.
A27: 23 | B27: Sholay CHS | C27: Andheri W | G27: Dropped | H27: Amit Wadhwani | I27: Redevelopment | K27: 0 | V27: -Vrushabh spoke, drop email -PMA, we have inroads, awaiting response
A28: 24 | B28: Shree Highland Park | C28: Kandivali | G28: Dropped | H28: Pradeep vasat (9819058565) | I28: Redevelopment | K28: 0 | V28: -Need to get data
A29: 25 | B29: Siddhivinayak CHS | C29: Kandivali W | G29: Dropped | H29: Agrawals | I29: Redevelopment | K29: 0 | V29: Feasibility to be prepared and shared with Mustakeen.
A30: 26 | B30: St. Pius | C30: Mulund W | G30: Dropped | H30: Ashok Borana | I30: Redevelopment | K30: 0 | V30: -PMC tender will come out -Site visit to be done in the week commencing 07/10
A31: 27 | B31: Suraiya Apartments | C31: Worli | G31: Dropped | H31: Colliers | I31: Redevelopment | K31: 0 | V31: FF Ready - meet with office bearers to understand next steps
A32: 28 | B32: Manju | C32: Sher-e-Punjab | G32: Dropped | H32: Inder | I32: Redevelopment | K32: 0 | L32: =INDEX('Opps combined list'!$1:$1048576,MATCH('Data Dump'!$B40,'Opps combined list'!$C:$C,0),MATCH('Data Dump'!L$4,'Opps combined list'!$4:$4,0)) -> #N/A | R32: =INDEX('Opps combined list'!$1:$1048576,MATCH('Data Dump'!$B40,'Opps combined list'!$C:$C,0),MATCH('Data Dump'!R$4,'Opps combined list'!$4:$4,0)) -> #N/A | S32: =INDEX('Opps combined list'!$1:$1048576,MATCH('Data Dump'!$B40,'Opps combined list'!$C:$C,0),MATCH('Data Dump'!S$4,'Opps combined list'!$4:$4,0)) -> #N/A | V32: Evaluated, not feasibile. Inder ji likes
A33: 29 | B33: Twinkle Star | C33: 0 | G33: Dropped | H33: 0 | I33: Redevelopment | K33: 0 | V33: 0
A34: 30 | B34: Unnat Nagar | C34: 0 | G34: Dropped | H34: BL Pandey | I34: Redevelopment | K34: 0 | V34: 0
A35: 31 | B35: Vaibhav Palace | C35: 0 | G35: Dropped | H35: 0 | I35: Redevelopment | K35: 0 | V35: -Dropped, not feasibile
A36: 32 | B36: Vitta Sanchay CHSL (Self Redevelopment) | C36: Chembur | E36: Shali | G36: Dropped | H36: Harshal Choudhary | I36: Redevelopment | K36: 0 | V36: Not Shortlisted
A37: 33 | B37: Kishori Court | C37: Worli Sea Face | G37: Dropped | H37: BL Pandey | I37: Outright | K37: 0 | V37: Dead
A38: 34 | B38: Rukiya Manzil Volkart House | C38: Warden Road | G38: Dropped | H38: BL Pandey | I38: Outright | K38: 0 | V38: Applied for PMC, survey to be conducted, feasibility prepared. (Dropped)
A39: 35 | B39: Devki Niwas CHSL | C39: Sion | E39: Sagar | G39: Dropped | H39: Pranay Kamat | I39: Redevelopment | K39: 503.35 | V39: Not Feasible
A40: 36 | B40: Neel Sagar | C40: Prabhadevi | G40: Slow Cooking | H40: Rajendra | K40: 516 | L40: 4.05 | M40: 33(11) | N40: 2089 | O40: 1057 | P40: 1032 | Q40: 67500 | R40: 7 | S40: 14 | T40: 69 | W40: Updated | X40: Updated
A41: 37 | B41: Dominic Condiminum | C41: Bandra | G41: Dropped | H41: 0 | I41: Redevelopment | K41: 516.7 | L41: 4.05 | M41: 33(7B )+ 33(12B) | N41: 2092.64 | O41: - | P41: 2093 | Q41: 60000 | T41: 126 | U41: Hunt | V41: Plot evaluated | W41: Updated | X41: Updated
A42: 38 | B42: Shishir | C42: Juhu | E42: Vru | G42: Dropped | H42: 0 | I42: Redevelopment | J42: Map | K42: 537 | L42: 5.4 | M42: 33(20B) | N42: 2900 | O42: 1316 | P42: 1462 | Q42: 85000 | R42: 17 | S42: 24 | T42: 123 | U42: Follow up | V42: Fitment requested from Foram
A43: 39 | B43: Gita | C43: Sion | G43: Dropped | H43: 0 | I43: Redevelopment | K43: 590 | V43: -Not feasible
A44: 40 | B44: Sunridges | C44: Juhu | E44: Vineet | G44: Dropped | H44: Varun | I44: JV/JD | J44: Maps | K44: 662 | L44: 5.4 | M44: 33(11) | N44: 3575 | O44: - | P44: 3575 | Q44: 60000 | S44: 13 | T44: 106
A45: 41 | B45: Ram Nagar | C45: Khar West | E45: Vineet | G45: Dropped | H45: Ravi Shekhar | I45: Redevelopment | K45: 694 | L45: 4.05 | M45: 33(11) | N45: 2811 | O45: 1029 | P45: 1782 | Q45: 45000 | R45: 6 | S45: 24 | T45: 84 | V45: Meeting with Elixir
A46: 42 | B46: Shree Ganesh Krupa | C46: Andheri West | G46: Dropped | I46: Redevelopment | K46: 752 | V46: Society has appointment some developer
A47: 43 | B47: Sangam - Sneh Sadan CHSL | C47: Borivali East | E47: - | G47: Dropped | H47: Ashok | I47: Redevelopment | K47: 764
A48: 44 | B48: Janak Kutir | C48: Dahisar | E48: Sagar | G48: Dropped | H48: Sanjay Khamkar | I48: Redevelopment | J48: Maps | K48: 845 | U48: The plot size is too small and develpers wont be intersted to work in this area with such small plot. Hence dropped
A49: 45 | B49: Saraswati Mahal | C49: Dadar | G49: Dropped | H49: Mr. P Thakur | I49: Redevelopment | K49: 859.26 | V49: -Set up meeting with Pompi Thakur -IM and feasibility to be prepared,reviewed and shared
A50: 46 | B50: Brindaban Dham | C50: Juhu | G50: Cold | I50: Redevelopment | J50: Maps | K50: 887 | L50: 5.4 | M50: 33(7B)+33(20B) | N50: 4791 | O50: 2162 | P50: 2630 | Q50: 60000 | R50: 25 | S50: 24 | T50: 156
A51: 47 | B51: Mangala Bhavan | C51: Juhu | G51: Dropped | H51: AOS | I51: Redevelopment | K51: 892 | V51: - Raunak is doing it -Follow up, Look for new options. *Kamal wadhwa - AOS not keen on gurunaam and Inspire
A52: 48 | B52: Ready Money , Walkeshwar | C52: Malabar Hills | D52: VS | E52: Vineet | G52: Dropped | H52: Pranay Kamat | J52: Maps | K52: 905 | L52: 5.4 | M52: 33(7B)+33(20B) | N52: 4342 | O52: 1976 | P52: =N52-O52 -> 2366 | Q52: 120000 | R52: 25 | S52: 70.68 | T52: 210 | U52: We are to get back to the broker with what number can be offered to the trust
A53: 49 | B53: Jeeta Bungalow | C53: Juhu | G53: Dropped | H53: Sameer Sata | I53: Outright / JV | K53: 905 | V53: -Feasibility to be prepared in our format: use the feasibility shared. | W53: Closed | X53: -
A54: 50 | B54: VIP | C54: Vile Parle East | D54: SBD | E54: Vineet | G54: Cold | I54: Redevelopment | J54: Maps | K54: 909.2 | L54: 3.04 | M54: 30(A) + 20(B) | N54: 2761 | O54: - | P54: 2761 | Q54: 30000 | R54: 22 | S54: 16 | T54: 87
A55: 51 | B55: Morumal Mansion CHSL, Khar | C55: Khar West | E55: SP | G55: Cold | H55: Dinesh | I55: JV/JD | J55: Maps | K55: 915
A56: 52 | B56: Mehta House Bungalow | C56: Juhu | G56: Dropped | I56: Outright | J56: Maps | K56: 940 | L56: 3.54 | M56: 30(A) + 20(B) | N56: 3372.6 | P56: 3328 | Q56: 90000 | V56: Pitch it to someone looking for bungalow
A57: 53 | B57: Bandra West SV Road Plot | C57: Bandra West | E57: Gaurang | G57: Active | H57: Source of Shubham | I57: Outright | J57: Maps | K57: 943.12 | M57: 33(11) | N57: 50434 | P57: 50434 | Q57: 50000 | R57: =696768849.568655/10^7 -> 69.676885 | S57: 68.5 | T57: 261 | V57: Very High price
A58: 54 | B58: Walkeshwar Bunglow | C58: Malabar Hills | E58: Vineet | G58: Dropped | H58: Sagar Salian | I58: Outright | J58: Maps | K58: 976 | L58: 5.4 | M58: 30(A) + 20(B) | N58: 5272 | O58: - | P58: 5272 | Q58: 120000 | R58: 258 | S58: 29 | T58: 626
A59: 55 | B59: Madhav Kunj Bungalow Plot | C59: Sion | E59: Gaurang | G59: Active | H59: Gaurang | I59: LL wants options from ANEX, Outright | J59: Maps | K59: 982 | L59: 5.4 | M59: 33(19), 33(11) | U59: Landlord wants an initial offer to convince his family. | V59: Meeting done on 18th Oct 2025. Evaluation to be done and options to be proposed to LL
A60: 56 | B60: Kailash Cottage & Shamdham Building | C60: Sion | G60: Dropped | H60: Sanjay Munyal | I60: Redevelopment | J60: Maps | K60: 984 | L60: 6.34 | M60: 33(7) | N60: 6241 | O60: 3104.66 | P60: 3137 | Q60: 35000 | R60: 14 | S60: 14 | T60: 108 | V60: Not Feasible
A61: 57 | B61: Samruddhi CHSL | C61: Mulund East | E61: Sagar | G61: Cold | H61: Avinash | I61: Redevelopment | K61: 1005 | L61: 5.4 | M61: 33(7B) +(20B) | N61: 5427 | O61: 1577 | P61: 3850 | Q61: 23000 | R61: 9.2 | S61: 6.3 | T61: 94
A62: 58 | B62: Vijay Bharat | C62: andheri west | E62: SP | G62: To be revived | H62: Sachinji Solanki | I62: Redevelopment | J62: Maps | K62: 1024 | L62: 5.4 | M62: 30(A)+20(B) | N62: 5529 | O62: 1382 | P62: 4147 | Q62: 40000 | R62: 14 | S62: 55 | T62: 176 | U62: Follow up | V62: No update from Sachin Solanki
A63: 59 | B63: Usha Villa | C63: Santacruz West | E63: Vineet | G63: Dropped | H63: Nihar Shah | I63: JV/JD | J63: Maps | K63: 1026 | L63: 5.4 | M63: 33(11) | N63: 5539 | O63: - | P63: 5539 | Q63: 70000 | R63: 161 | S63: 95 | T63: 455
A64: 60 | B64: Yashashree CHSL | C64: Bandra East | E64: Abhinav | G64: Dropped | H64: Soni | I64: Redevelopment | K64: 1070 | V64: get in touch with Satish Soni and speak to Society (prob - 4 units)
A65: 61 | B65: Bharat Mansion | C65: Matunga | E65: Vineet | G65: WIP | H65: Dinesh & Nihal | K65: 1149 | V65: Exisiting developer in place, feasibility to be made and terms to be understood
A66: 62 | B66: Divya Jyot | C66: Andheri East | E66: SP | F66: PMC | G66: Won | H66: Kaushal | I66: Redevelopment | J66: Maps | K66: 1212
A67: 63 | B67: Jasmine & Moonira lodge | C67: Colaba Causeway | E67: Sagar | G67: Dropped | H67: Vijay Mundra & Naveen Parikh | I67: JV/JD | J67: Maps | K67: 1270.91 | L67: 5.4 | M67: 33(7) + 33(12B) | N67: 6533 | O67: 2421 | P67: 4112 | Q67: 110000 | R67: 110 | S67: 110 | T67: 336 | U67: Hunt | V67: Tentative Feasibility Signed off from Architect
A68: 64 | B68: Guru Angad Tower | C68: Dindoshi | E68: Gaurang | G68: Dropped | H68: Amit Kabre | I68: Redevelopment | J68: Maps | K68: 1314 | L68: 5.4 | M68: 33(7B)+33(20B) | N68: 7094 | O68: 2020 | P68: 5094 | Q68: 30000 | R68: 13 | S68: 23 | T68: 150 | U68: Pipe access. Need to merge with other society
A69: 65 | B69: Bayview Apartments | C69: Bandra W | G69: Dropped | H69: Naresh Rohira | I69: Redevelopment | K69: 1336 | V69: -Pitch to VKG, Inspire, Raunak, Siroya, Shri Krishna Group (Nisha) -Feasibility and IM shared with NCC Urban and L&T, Ekta, Raymond (hot), Drop all. CP: Pratik to be contacted for the redevelopment.
A70: 66 | B70: Santacruz Saryu Co Housing Society | C70: Santacruz | G70: Pending | K70: 1400.5 | M70: To be evaluated
A71: 67 | B71: Parmanand Society | C71: Khar west | E71: Gaurang | G71: Not Active | I71: Redevelopment | J71: Maps | K71: 1454 | M71: 30A | N71: 53324 | O71: 22413 | P71: 28438 | Q71: 58000 | R71: 15 | S71: 28 | T71: 165 | V71: Feasibility done. To be revieweed
A72: 68 | B72: Om Shanti CHS | C72: Santacruz | E72: Gaurang | G72: Dropped | H72: Vijay Vohra | I72: Redevelopment | J72: Maps | K72: 1497 | L72: 3 | M72: 33(7 B)+ 33 (20B) | N72: 1497 | O72: 4181 | P72: 1729 | Q72: 52000 | R72: 21 | S72: No Profit | T72: 97 | V72: Highly overconsumed FSI.
A73: 69 | B73: Mohammadi Apartments | C73: Malad E | G73: Dropped | H73: 0 | I73: Redevelopment | K73: 1517 | V73: - FF Ready, share with developers
A74: 70 | B74: Agarwal's Borivali | C74: Borivali East | E74: Vineet | G74: WIP | H74: Agarwals | J74: Maps | K74: 1529 | M74: 33(19)
A75: 71 | B75: Swagat Park | C75: Goregaon | E75: Shubham/ Gaurang | G75: Cold | I75: SRA | J75: Maps | K75: 1540 | L75: 4 | M75: 33(10) & 30(A) + 30B | N75: 170048 | O75: 38254 | P75: 131794 | Q75: 28000 | R75: 41 | S75: 71 | T75: 367 | V75: Feasibility done. To be revieweed
A76: 72 | B76: Milan Milap | C76: Juhu | G76: Dropped | H76: 0 | I76: Redevelopment | K76: 1541.6 | V76: 0
A77: 73 | B77: Jayshree SBI | C77: Worli | G77: Dropped | H77: Chetan | I77: Outright | K77: =1600 -> 1600 | V77: To follow up with Sachin on offer by his client - meeting with society on 07/10
A78: 74 | B78: Noorani Building | C78: Mahim West | E78: Sagar | G78: Dropped | H78: Harshad Dalvi | I78: JV/JD | J78: Maps | K78: 1604 | L78: 5.4 | M78: 33(7) | N78: 8663.92 | V78: Have informed Harshad Dalvi that the project has been dropped
A79: 75 | B79: Jayshree Apartments | C79: Worli | E79: Vineet | G79: Revive | H79: Chetan Shah | I79: Outright | J79: Maps | K79: 1672 | L79: 5.4 | M79: 30(A)+20(B) | N79: 9029 | O79: - | P79: 9029 | Q79: 150000 | R79: 6 | S79: 337 | T79: 1341
A80: 76 | B80: Sea Glimpse | C80: Worli | E80: Vineet | G80: Cold | H80: Sachin | K80: 1696
A81: 77 | B81: Shopper Stop | C81: Andheri | E81: Sagar | G81: Dropped | H81: Nihar | J81: Maps | K81: 1697 | M81: 33(11) | V81: WIP
A82: 78 | B82: Kothari Niwas | C82: Ghatkopar | D82: Sagar | E82: Vineet | G82: Cold | H82: Sanjay Khamkar | I82: Redevelopment | J82: Maps | K82: 1711 | L82: 4.05 | M82: 33(19) | N82: 6929.96 | O82: 1230.94 | P82: 5699.02 | Q82: 45000 | R82: 27 | S82: 24 | T82: 169
A83: 79 | B83: Bandstand Apartments | C83: Bandra | E83: SP | G83: Dropped | I83: Redevelopment | K83: 1749 | U83: wait | V83: Awaiting appointment as PMC
A84: 80 | B84: Rajiv CHS | C84: Bandra East | E84: Sagar | G84: Won | I84: Redevelopment | J84: Maps | K84: 1787 | L84: 5.4 | M84: 33(7B) +20(B) | N84: 9652 | O84: 2800 | P84: 6694 | Q84: 40000 | R84: 25 | S84: 42 | T84: 265 | U84: Follow up | V84: -Updated forma to be shared with Society
A85: 81 | B85: Kiran Villa | C85: Peddar Road | G85: Dropped | H85: Colliers | I85: Redevelopment | K85: 1787 | V85: -Meet landowner after Diwali -FF Ready - meet with office bearers to understand next steps
A86: 82 | B86: Labh Niwas & Subh Niwas CHSL | C86: Ghatkopar | E86: SP | G86: Slow Cooking | H86: Ashok Borana | I86: Redevelopment | K86: 1899.5 | L86: 4.05 | M86: 33(19) | N86: 7693 | O86: 2742 | P86: 4951 | Q86: 40000 | R86: =INDEX('Opps combined list'!$1:$1048576,MATCH('Data Dump'!$B34,'Opps combined list'!$C:$C,0),MATCH('Data Dump'!R$4,'Opps combined list'!$4:$4,0)) -> #N/A | S86: =INDEX('Opps combined list'!$1:$1048576,MATCH('Data Dump'!$B34,'Opps combined list'!$C:$C,0),MATCH('Data Dump'!S$4,'Opps combined list'!$4:$4,0)) -> #N/A | T86: 199 | U86: Follow up and close | V86: Meet with Ashok and understand next steps
A87: 83 | B87: AB Chawl | C87: Lower Parel | D87: Sahil | E87: Vineet | G87: Dropped | H87: Neelam | I87: Redevelopment | J87: Maps | K87: 1994 | L87: 5.67 | M87: 33(7) | N87: 11313 | P87: 48016 | Q87: 80000 | R87: 123 | S87: 22 | T87: 384
A88: 84 | B88: Napean House | C88: Malabar hills | E88: Sahil | G88: Cold | H88: Neelam | I88: Outright | J88: Maps | K88: 2006 | L88: 5.4 | M88: 33(7) + 20(B) | N88: 10863 | P88: 10863 | Q88: 150000 | R88: 613 | S88: 257 | T88: 1609
A89: 85 | B89: Maker Mahal | C89: Bandra West | E89: Sagar | G89: Closed | I89: Outright | J89: ='[1]Reg. 33(11)'!I39 -> 0 | K89: 2025.9 | L89: 5.4 | M89: 30(A) + 20(B) | N89: 9154.62 | O89: 0 | P89: 9154.62 | Q89: 80000 | T89: 800 | U89: Follow up | V89: Set meeting with Landowner
A90: 86 | B90: Sea Mist | C90: Bandra West | D90: VS | E90: Vineet | G90: Slow Cooking | H90: Sachin | I90: Redevelopment | J90: Maps | K90: 2036 | L90: 5.4 | M90: 33(11) | N90: 10992 | O90: 6154 | P90: 4837 | Q90: 70000 | R90: 55 | S90: 47 | T90: 342
A91: 87 | B91: Laxminarayan & Devlok & Devdeep (new) | C91: Santacruz W | D91: SBD | E91: Vineet | G91: Slow Cooking | H91: Sameer Sata | I91: Redevelopment | J91: Maps | K91: 2045.85 | L91: 5.4 | M91: 33(7B) + 33(20B) + 33(12B) | N91: 20643 | O91: 8871 | P91: =N91-O91 -> 11772 | Q91: 57500 | R91: 69 | S91: 100 | T91: 670 | U91: Follow up and close | V91: Met Palash. No movement.
A92: 88 | B92: New Jal Darshan | C92: Bandra W | E92: Shali | F92: PMC | G92: Dropped | H92: Sachin Agrawal | I92: Redevelopment | J92: Maps | K92: 2053.2 | L92: 4.05 | M92: 33(11) | N92: 8315.46 | O92: 4113.5909 | P92: 3670.8419 | Q92: 80000 | R92: 28 | S92: 82 | T92: 290 | U92: Follow up | V92: Met society, Impase continues
A93: 89 | B93: Manav Mandir | C93: Worli | E93: Sagar | G93: Dropped | H93: Pranay Kamat | I93: Redevelopment | K93: 2090 | L93: 5.4 | M93: 33(11) | N93: 11288 | O93: 3861 | P93: 7427 | Q93: 72000 | R93: 52 | S93: 114 | T93: 529 | V93: Society and PMC not Aligned
A94: 90 | B94: Pestom Sagar (New Nataraj CHSL) | C94: Chembur | E94: Sagar | G94: Dropped | H94: Hardik | I94: Redevelopment | J94: Maps | K94: 2099 | L94: 5.4 | M94: 33(7) + 20(B) | N94: 11335 | O94: 2808 | P94: 8369 | Q94: 25000 | R94: 20.2 | S94: 29.8 | T94: 210 | V94: Next steps to be understood | Y94: Ashadeep
A95: 91 | B95: Rajamata Jijamata (Nathkrupa) | C95: Chembur | E95: Sagar | G95: Active | H95: Agarwals | I95: Redevelopment | K95: 2100 | L95: 5.4 | M95: 33(11) | N95: 11339 | O95: 3108 | P95: 8231 | Q95: 28000 | R95: 32 | S95: 28 | T95: 228 | V95: Bid by Agarwals
A96: 92 | B96: Cama Industrial Estate, Goregaon | C96: Goregaon | D96: Sagar | E96: Vineet | G96: Active | H96: Satishji Soni | J96: Maps | K96: 2111.76 | L96: 5.4 | M96: 33(19) | N96: 10263.15 | O96: - | P96: 10263 | Q96: 27000 | S96: 35 | T96: 230
A97: 93 | B97: Khar Redevelopment | C97: Khar Road | G97: Pending | H97: Nihal | I97: Outright | K97: 2153.8 | M97: To be evaluated
A98: 94 | B98: New Creation Society Khar | C98: Khar | E98: Gaurang | G98: Dropped | I98: Redevelopment | J98: Maps | K98: 2153.84 | L98: 4 | M98: 33(11) & 33(19) | N98: 8723 | O98: 2860 | P98: 5140 | Q98: 50000 | R98: 42 | S98: 52 | T98: 283 | V98: Meeting to be done with society. Following up
A99: 95 | B99: New Haven | C99: Andheri W | E99: SP | G99: Revive | H99: Vinay | K99: 2252 | V99: Awaiting response from Vinay
A100: 96 | B100: Monalisa Co Housing Society | C100: Bandra | E100: Gaurang | G100: Evaluated | H100: Ref. Mr. Rashid through Harshad Dalvi | I100: Redevelopment | J100: Maps | K100: 2339.66 | L100: 4.05 | M100: 33(7B) + 20B | N100: 9475.623 | O100: 7662.2159 | P100: 1810.181 | Q100: 60000 | R100: =396355792.436244/10^7 -> 39.635579 | S100: =-1468225986.2982/10^7 -> -146.8226 | T100: =1107816800.22382/10^7 -> 110.78168 | U100: Only 20% of the BUA remaining for Sale
A101: 97 | B101: Shree Niketan | C101: Santacruz W | E101: Shali | G101: Slow Cooking | H101: Sameer Sata | I101: Redevelopment | J101: Maps | K101: 2416 | L101: 5.4 | M101: 33(11) | N101: 13046 | O101: 0 | P101: 13046 | Q101: 75000 | R101: 318 | S101: 246 | T101: 1075 | U101: Follow up | V101: Crest has put in a offer
A102: 98 | B102: Prahlad CHSL | C102: Santacruz | E102: Vineet | G102: Active | H102: Prem | I102: Redevelopment | J102: Maps | K102: 2418.71 | L102: 5.4 | M102: 33(11) | N102: 12521 | O102: 4733 | P102: 7541 | Q102: 65000 | R102: 113 | S102: 74 | T102: 450 | U102: Hunt | V102: draft Tender shared with society
A103: 99 | B103: Sahar Prabhudayal | C103: Andheri | D103: SP | E103: Vineet | G103: Dropped | H103: Agarwals | I103: Redevelopment | J103: Maps | K103: 2486 | L103: 4.05 | M103: 33(7B) +20(B) | N103: 8856 | O103: 3571 | P103: 5285 | Q103: 40000 | R103: 25 | S103: 11 | T103: 195
...

Sheet List for Casa
C3: List of Opportunities
C6: Name of Society | D6: Deal Type | E6: Location | F6: Location Pin | G6: Plot size (sq.m.) | H6: Regulation Proposed | I6: Topline (in Crores) | K6: Comment
C7: Vinay Industrial Estate | D7: Redevelopment | E7: Malad West | F7: Maps | G7: 4688.2 | H7: 33(19) | I7: 753 | K7: Commercial not interested
C8: Singh Estate | D8: Outright + Redevelopment | E8: Dadar East | F8: Maps | G8: 7562.71 | H8: 33(9) | I8: 1160 | K8: Site Visit Proposed
C9: CSP & Chakreshwari CHSL | D9: Redevelopment | E9: Mulund West | F9: Maps | G9: 10429 | H9: 33(9) | I9: 935 | K9: Not Interested, no margins, 32000 too high
C10: Deepak Jyoti Parel | D10: Redevelopment | E10: Parel | F10: Maps | G10: 12080.7 | H10: 33(9) | I10: 1643 | K10: Risk with the Title with the Trust
C11: Diwan Land | D11: Outright | E11: Marol | F11: Maps | G11: 8743 | H11: 33(19) | I11: 1324 | K11: JV/JD preference
C12: Ruby Apartments | D12: Outright + Redevelopment | E12: Juhu | F12: Maps | G12: 1765.5 | H12: 33(7B)+33(20B) | I12: 416 | K12: Interested - FF - Legal Query
C13: Powai | D13: Outright + Redevelopment | E13: Powai | F13: Maps | G13: 33364.8 | H13: 33(11) | I13: 5700 | K13: Avoid Mangesh
C14: LIC Colony | D14: Redevelopment | E14: Mulund West | F14: Maps | G14: 15804.7 | H14: 33(9) | I14: 1180 | K14: Interested - FF - Sale Rate - 25K - Conveyance
C15: Dakshin Pali | D15: Redevelopment | E15: Bandra West | F15: Maps | G15: 3854.6 | H15: 33(7B)+33(12B) | I15: 834 | K15: Interested - FF - Legal Query
C16: Manish Nagar | D16: Redevelopment | E16: Andheri W | F16: Maps | G16: 40000 | H16: 33(9)
C17: Wise City | D17: Outright | E17: Panvel | F17: Maps | K17: Corporate Sturture Query
C18: Adarsh Nagar | D18: Redevelopment | E18: Worli | F18: Maps
C19: Goregaon Commercial | D19: JV/JD | E19: Goregaon | F19: Maps | G19: 15000 | H19: 33(10)
C20: Shedung land

Sheet Manish and Juhu
F3: Manish Nagar
F4: Developer | G4: Status
F5: Birla
F6: Sobha
F7: Raymond
F8: My Home
F9: Casagrande
F10: Sattva
F11: Embassy
F12: Ramky
F13: Piramal
F14: Purvankara
F15: Kalpataru
F16: Wadhwa
... F20: HOH

Sheet Neelam, Nitul, Ajay, Harshad
B2: Property | C2: Location | D2: Maps | E2: Plot Area | F2: Sourcing Partner
B3: BPL | C3: Matunga | D3: Maps | E3: 2584 | F3: Ajay Vora
B4: Karanjade Land | C4: JNPT, Navi Mumbai | F4: Ajay Vora
B5: CSP & Chakreshwari CHSL | C5: Mulund West | D5: Maps | E5: 10429 | F5: Dipen
B6: Punjab Society | C6: Santacruz West | E6: 4017 | F6: Dipen
B7: Shivam Complex Vashi | C7: Vashi | D7: Maps | E7: 3493 | F7: Harshad Dalvi
B8: Noorani Building | C8: Mahim West | D8: Maps | E8: 1604 | F8: Harshad Dalvi
B9: Roshan Apartments | C9: Borivali East | E9: - | F9: Harshad Dalvi
B10: Koregaon Park Redevelopment | C10: Pune | E10: ~3.5 Acre | F10: Harshad Dalvi
B11: AB Chawl | C11: Lower Parel | D11: Maps | E11: 1994 | F11: Neelam Sanghvi
B12: Napean House | C12: Malabar Hill | D12: Maps | E12: 2006 | F12: Neelam Sanghvi
B13: Walkeshwar Cluster | C13: Malabar Hills | D13: Maps | E13: - | F13: Neelam Sanghvi
B14: Worli Church Property | C14: Worli | D14: Maps | E14: 2648 | F14: Neelam Sanghvi
B15: Navyug Nagar | C15: Tardeo | D15: Maps | E15: 4942 | F15: Neelam Sanghvi
B16: Empire Guide | C16: Malabar hills | D16: Maps | E16: 4006 | F16: Neelam Sanghvi
B17: Giriraj | C17: Malabar hills | E17: - | F17: Neelam Sanghvi
B18: AAI Property | C18: Andheri East | E18: ~5.5 Acre | F18: Nitul
B19: Bapsola / Noor E Rehmat | C19: Bandra West | D19: Maps | E19: 1865 | F19: Nitul
B20: Anand Nagar | C20: Dahisar | E20: - | F20: Nitul

Sheet PMC-PMA 
B2: Name of Society | C2: Location | D2: Location Pin | E2: Plot size (sq.m.) | F2: Regulation Proposed | G2: Engagement
A3: 5 | B3: Triveni CHSL | C3: Mulund West | D3: Maps | F3: 33(9) | G3: PMC
A4: 1 | B4: Prahlad CHSL | C4: Santacruz West | D4: Maps | E4: 2418.71 | F4: 33(11) | G4: PMC
A5: 1 | B5: Ayodhya CHSL | C5: Lower Parel | D5: Maps | E5: 4278.91 | F5: 33(7) + 33(9) | G5: PMC
A6: 1 | B6: Dudhsagar CHSL | C6: Goregaon East | D6: Maps | E6: 19976.72 | F6: 33(9) | G6: PMA
A7: 1 | B7: Mahindra CHSL | C7: Malad East | D7: Maps | E7: 58367 | F7: 33(9) | G7: PMA
A8: 1 | B8: Khajuria CHSL | C8: Kandivali West | D8: Maps | E8: 11895.33 | F8: 30(A) + 33(20B) + 17 | G8: PMA
A9: 1 | B9: New Jal Darshan | C9: Bandra West | D9: Maps | E9: 2053.2 | F9: 33(11) | G9: PMC
A10: 1 | B10: Rajiv | C10: Bandra East | D10: Maps | E10: 1787 | F10: 33(7B) +20(B) | G10: PMC
A11: 1 | B11: Divya Jyot | C11: Andheri East | D11: Maps | E11: 1212 | F11: 33(10) | G11: PMC
A12: 3+1 | B12: Manish Nagar | C12: Andheri West | D12: Maps | E12: 7620 | F12: 33(7B) +20(B) | G12: PMC
A13: 4 | B13: Lokhandwala Cluster | G13: PMC
A14: 1 | B14: Samarth Nagar | G14: PMA
A15: 1 | B15: Gloma | G15: PMC

Sheet Opps combined list
C1: List of Opportunities
C4: Name of Society | D4: Location | E4: Deal Type | F4: Location Pin | G4: Plot size (sq.m.) | H4: FSI Potential | I4: Regulation Proposed | J4: Development Potential (sq.m.) | K4: Rehab Area (sq.m.) | L4: Sale Area (sq.m.) | M4: Sale Rate Considered (psf) | N4: Initial Investment | O4: Profit | P4: Topline (in Crores)
C5: 2 Acre Kalina | D5: Santacruz East | E5: Outright | F5: Maps | G5: 9991 | H5: 6.75 | I5: 33(19) | J5: 60695.325 | K5: 0 | L5: 60695.325 | M5: 50000 | P5: 300
C6: Aangan & Maryland | D6: Sion East | E6: Society Redevelopment | F6: Map | G6: 3508 | H6: 5.4 | I6: 33(11) | J6: 18945 | K6: 7314 | L6: 11599 | M6: 35000 | P6: 580
C7: Ambedkar Nagar CHSL | D7: Worli | E7: Society Redevelopment | F7: Maps | G7: 9311 | H7: 5.4 | I7: 33(5) | J7: 43212 | K7: 20196 | L7: 23015 | M7: 65000 | N7: 90 | O7: 235 | P7: 1481
C8: ARC - Daya | D8: Goregaon East | E8: Outright | F8: Maps | G8: 6032 | H8: 2.97 | I8: 30(A) + 17(1) | J8: 22846 | K8: 2227 | L8: 20619 | M8: 30000 | N8: 83 | O8: 170 | P8: 612
C9: Ashokraj Topiwala Washington | D9: Goregaon West | E9: Society Redevelopment | F9: Maps | G9: 6737 | H9: 5.4 | I9: 33(9) | J9: 46317 | K9: 19869 | L9: 24363 | M9: 33315 | N9: 84 | O9: 171 | P9: 676
C10: Ayodhya CHSL | D10: Lower Parel | E10: Society Redevelopment | F10: Maps | G10: 4278.91 | H10: 7.02 | I10: 33(7) + 33(9) | J10: =30028 -> 30028 | K10: 13841 | L10: =162021/10.764 -> 15052.118 | M10: 42500 | P10: 681 | Q10: =SUM(K10+L10) -> 28893.118 | R10: =J10-Q10 -> 1134.8818
C11: Bara Chawl + Topowan | D11: Lower Parel | E11: SRA | F11: Maps | G11: 4215.76 | H11: 14.04 | I11: 33(9) | J11: 59205 | K11: 27456 | L11: 31703 | M11: 42000 | P11: 1459
C12: Bezzola Complex | D12: Chembur | E12: Society Redevelopment | F12: Maps | G12: 11502.2 | H12: 6.75 | I12: 33(19) | J12: 77639.85 | K12: 16875.72 | L12: 60730.1 | M12: 32500 | P12: 1922
C13: Borla | D13: Chembur | E13: Society Redevelopment | F13: Maps | G13: 13890.2 | H13: 5.4 | I13: 33(9) | J13: 75007 | K13: 22486 | L13: 52521 | M13: 42000 | P13: 2400
C14: Brindaban Dham | D14: Juhu | E14: Society Redevelopment | F14: Maps | G14: 887 | H14: 5.4 | I14: 33(7B)+33(20B) | J14: 4791 | K14: 1129 | L14: 2162 | M14: 60000 | P14: 156 | Q14: =SUM(K14+L14) -> 3291 | R14: =J14-Q14 -> 1500
C15: Dominic Condiminum | D15: Bandra West | E15: Outright | F15: Map | G15: 516.7 | H15: 4.05 | I15: 33(7B )+ 33(12B) | J15: 2092.64 | K15: - | L15: 2093 | M15: 60000 | P15: 126
C16: Gandhi Market | D16: Sion | E16: Society Redevelopment | F16: Maps | G16: 5894.7 | H16: 6.26 | I16: 33(9) | J16: 34209 | K16: 16687 | L16: 17521 | M16: 45000 | P16: 780
C17: Goshala road Cluster | D17: Mulund West | E17: Society Redevelopment | F17: Map | G17: 3394.3 | H17: 5.4 | I17: 33(7B) + 33(20B) | J17: 18182.502 | K17: 6091.585 | L17: 10919.383 | M17: 23000 | P17: 250 | Q17: =SUM(K17+L17) -> 17010.968 | R17: =J17-Q17 -> 1171.5336
C18: Harshad CHSL | D18: Sion East | E18: Society Redevelopment | F18: Maps | G18: 2989 | H18: 5.4 | I18: 30(7B) + 20(B) | J18: 16141 | K18: 4044 | L18: 12097 | M18: 28000 | N18: 25 | O18: 79 | P18: 340
C19: Jasmine & Moonira lodge | D19: Colaba Causeway | E19: JV/JD | F19: Maps | G19: 1270.91 | H19: 5.4 | I19: 33(7) + 33(12B) | J19: 6533 | K19: 2421 | L19: 4112 | M19: 110000 | N19: 110 | O19: 110 | P19: 336
C20: JVLR Cluster | D20: Jogeshwari East | E20: Society Redevelopment | F20: Maps | G20: 7276 | H20: 7.1 | I20: 33(9) | J20: 51909 | K20: 25624 | L20: 26588 | M20: 31000 | P20: 1021 | Q20: =SUM(K20+L20) -> 52212 | R20: =J20-Q20 -> -303
C21: Khajuria Nagar | D21: Kandivali West | E21: Society Redevelopment | F21: Maps | G21: 11895.33 | H21: 5.4 | I21: 30(A) + 33(20B) + 17 | J21: 58298.994 | K21: 11567.197 | L21: 45528.808 | M21: 27000 | N21: 60 | O21: 250 | P21: 1218 | Q21: =SUM(K21+L21) -> 57096.006 | R21: =J21-Q21 -> 1202.9885
C22: Labh Niwas & Subh Niwas CHSL | D22: Ghatkopar East | E22: JV/JD | F22: Maps | G22: =1899.5 -> 1899.5 | H22: 4.05 | I22: 33(19) | J22: 7693 | K22: 2742 | L22: 4951 | M22: 40000 | P22: 199
C23: Laxminarayan & Devlok | D23: Santacruz West | E23: Society Redevelopment
C24: Lokhandwala Cluster | D24: Andheri West | E24: Society Redevelopment | F24: Maps | G24: 16932 | H24: 6.8 | I24: 33(9) | J24: 114595 | K24: 52197 | L24: 60026 | M24: 45000 | P24: 2722 | Q24: =SUM(K24+L24) -> 112223 | R24: =J24-Q24 -> 2372
C25: Mahindra Nagar | D25: Malad East | E25: Society Redevelopment | F25: Maps | G25: 58367 | H25: 5.4 | I25: 33(9) | J25: 179143 | K25: 53217 | L25: 93254 | M25: 30000 | P25: 3700 | Q25: =SUM(K25+L25) -> 146471 | R25: =J25-Q25 -> 32672
C26: Maker Mahal | D26: Bandra West | E26: Outright | F26: Maps | G26: 2025.9 | H26: 5.4 | I26: 30(A) + 20(B) | J26: 9154.62 | K26: 0 | L26: 9154.62 | M26: 80000 | N26: 173 | O26: 186 | P26: 800
C27: Manish Nagar | D27: Andheri West | E27: Society Redevelopment | F27: Maps | G27: 10217 | H27: 5.4 | I27: 33(9) | J27: 55172 | K27: 16161 | L27: 36671 | M27: 35000 | P27: 1270 | Q27: =SUM(K27+L27) -> 52832 | R27: =J27-Q27 -> 2340
C28: Mon Desire | D28: Bandra west | E28: Society Redevelopment
C29: Nalanda CHSL | D29: Malad West | E29: Society Redevelopment | F29: Maps | G29: 6680 | I29: 33(9) | J29: 34605 | K29: 12686.56 | Q29: =SUM(K29+L29) -> 12686.56 | R29: =J29-Q29 -> 21918.44
C30: Narayana Guru CHS | D30: Chembur | E30: Society Redevelopment | F30: Maps | G30: 9486 | H30: 4.94 | I30: 33(9) | J30: 46878 | K30: 13449 | L30: 25812 | M30: 24000 | P30: 731 | Q30: =SUM(K30+L30) -> 39261 | R30: =J30-Q30 -> 7617
C31: New Jal Darshan | D31: Bandra West | E31: Society Redevelopment | F31: Maps | G31: 2053.2 | H31: 4.05 | I31: 33(11) | J31: 8315.46 | K31: 4113.5909 | L31: 3670.8419 | M31: 80000 | P31: 290 | Q31: =SUM(K31+L31) -> 7784.4328 | R31: =J31-Q31 -> 531.02719
C32: Nityanand Bagh | D32: Chembur | E32: Society Redevelopment | F32: Maps | G32: 15348 | H32: 5.4 | I32: 33(9) | J32: 77973 | K32: 25838 | L32: =J32-K32 -> 52135 | M32: 30000 | P32: 1650
C33: Prahlad CHSL | D33: Santacruz West | E33: Society Redevelopment | F33: Maps | G33: 2418.71 | H33: 5.4 | I33: 33(11) | J33: 12521 | K33: 4733 | L33: 7541 | M33: 65000 | N33: 79 | O33: 113 | P33: 513 | Q33: =SUM(K33+L33) -> 12274 | R33: =J33-Q33 -> 247
C34: Rajendra Park CHS | D34: Goregoan West | E34: Society Redevelopment | F34: Maps | G34: 6777.82 | H34: 5.4 | I34: 33(9) | J34: 32322.205 | K34: 8246.8985 | L34: 24075.307 | M34: 31500 | P34: 780
C35: Redstone | D35: Juhu | E35: JV/JD | F35: Maps | G35: 1392 | H35: 5.4 | I35: 30(A)+33(20B) | J35: 7517 | K35: - | L35: 7517 | M35: 65000 | N35: 120 | O35: 77 | P35: 386
C36: Sagar CHSL | D36: Mahim | E36: Society Redevelopment | F36: Maps | G36: 4229 | H36: 6.62 | I36: 33(5) | J36: 27371 | K36: 12415 | L36: 14956 | M36: 42000 | P36: 622
C37: Shree Niketan | D37: Santacruz West | E37: Society Redevelopment | F37: Maps | G37: 2416 | H37: 5.4 | I37: 33(11) | J37: 13046 | K37: 0 | L37: 13046 | M37: 75000 | P37: 1075
C38: Shree Ram | D38: Andheri West | E38: Society Redevelopment | F38: Maps | G38: 13882 | H38: 3.3 | I38: 33(7B) | J38: 42900 | K38: 14992 | L38: 27811 | M38: 38000 | N38: 112 | O38: 216 | P38: 1101 | Q38: =SUM(K38+L38) -> 42803 | R38: =J38-Q38 -> 97
C39: Snehadhara CHSL | D39: Santacruz West | E39: Society Redevelopment | F39: Maps | G39: 12955.6 | H39: 3 | I39: 33(11) | J39: 39352.635 | K39: 16036.395 | L39: 20232.12 | M39: 44000 | P39: 970 | Q39: =SUM(K39+L39) -> 36268.515 | R39: =J39-Q39 -> 3084.1196
C40: Sumer Nagar | D40: Borivali | E40: Society Redevelopment | F40: Maps | G40: 12662 | H40: 5.4 | I40: 33(9) | J40: 68375 | K40: 31810 | L40: 36569 | M40: 35000 | P40: 1330
C41: Tolaram | D41: Chembur | E41: Society Redevelopment | F41: Maps | G41: 18618 | H41: 5.4 | I41: 33(9) | J41: 89173 | K41: 18295 | L41: =J41-K41 -> 70878 | M41: 30000 | P41: 2000
C42: Woodstock CHSL | D42: Versova | E42: Society Redevelopment | F42: Maps | G42: 6653 | H42: 5.1 | I42: 33(9) | J42: 33941 | K42: 9893 | L42: 20824 | M42: 50000 | P42: 1120 | Q42: =SUM(K42+L42) -> 30717 | R42: =J42-Q42 -> 3224

Sheet Proposal Tracker
G1: x | H1: o | I1: ☑ | J1: S | K1: i
G2: Declined | H2: Sent | I2: EOI Rec. | J2: To be Sent | K2: interested
B4: Status | D4: PoC - 1 | E4: PoC - 2 | F4: Runwal - Sandeep | G4: Runwal - Subodh | H4: Sobha | I4: L&T | J4: Mahindra | K4: HOH | L4: Kolte Patil | M4: Sattva | N4: Ramky | O4: Crest | P4: Prescon | Q4: NCC | R4: Sunteck | S4: VKG | T4: Kabra | U4: Raymond | V4: SKS Anchor Point | W4: Moongipa | X4: Kanakia | Y4: Hines | Z4: H.rishabhraj | AA4: Aditya Birla | AB4: Veena | AC4: DGS | AD4: K Raheja | AE4: Matrix | AF4: Kohinoor | AG4: Greenscape | AH4: Sonal | AI4: Q group | AJ4: Raheja Homes | AK4: Silver | AL4: Bluekey realty | AM4: Arkade | AN4: Lloyds | AO4: Sugee | AP4: Aditya Raj | AQ4: Pushpa Raj | AR4: Mass Group | AS4: Sumukha | AT4: Arth | AU4: Sai | AV4: Om | AW4: Mohite | AX4: Tater World | AY4: AVSN | AZ4: B-right | BA4: Puri Creators | BB4: Paradigm | BC4: Maniar | BD4: Agami | BE4: K Nagpal | BF4: Piramal | BG4: Kalpataru | BH4: Sheth | BI4: Tribeca | BJ4: Supreme | BK4: Woodstock | BL4: Akshay Group | BM4: JSW | BN4: Shree Malli Realty | BO4: Authum Infra
B5: 1 | C5: 17Acre Versova | D5: Shalibhadra | E5: Vineet | K5: S | M5: S
C6: Ambedkar Nagar, Worli | F6: x | G6: i | H6: S | I6: i | J6: o | K6: o | L6: i | M6: i | N6: ☑ | Q6: o | T6: o | AK6: o
C7: Aminia | N7: o | O7: o | AD7: o
C8: Anand Nagar Santacruz | N8: o | S8: o | W8: o
C9: Borla | H9: ☑ | I9: o | J9: o | K9: X | L9: X | M9: X | N9: ☑ | Q9: o
C10: Jasmine (JV/JD) | F10: x | G10: x | J10: o | K10: S | L10: S | M10: S | N10: o | P10: o
C11: Khajuria Nagar | F11: o | G11: o | I11: S | J11: S | K11: S | L11: S | N11: o
C12: Madhugiri | N12: o | AW12: o | AX12: o
C13: Moray House | O13: o
C14: Navyug - Forjett | G14: o | H14: o | N14: o | X14: o | AA14: o | AB14: o | AD14: o | AN14: o
C15: New Jal Darshan | G15: i | H15: S | I15: o | J15: S | K15: S | L15: S | M15: S
C16: Nityanand Baug | G16: x | H16: o | I16: o | J16: o | K16: S | L16: i | M16: X | N16: o | Q16: ☑ | R16: o | T16: o | U16: o | V16: o | X16: o | Z16: o | AB16: o | AI16: o | AM16: o
C17: Prahlad CHSL - Santacurz | H17: o | I17: o | K17: S | L17: S | M17: S | N17: o | Q17: o
C18: Rajendra Park & Nalanda Mall, Goregaon (West) | F18: i | G18: o | J18: X | L18: o | M18: x | Q18: o | S18: o | T18: o | V18: o | X18: o | Z18: o | AB18: o | AH18: o | AI18: o | AZ18: o
C19: Sagar, Mahim | J19: S | P19: o | Q19: o | T19: o | W19: o | X19: o | AK19: o | AL19: o
C20: Shree Ram CHSL, Andheri (West) | I20: i | J20: S | K20: ? | L20: ☑ | M20: i | N20: ☑ | Q20: ☑
C21: Snehdhara | L21: o | N21: ☑ | Q21: ☑
C22: Sumer Nagar | F22: i | G22: o | H22: o | I22: o | J22: o | K22: X | L22: o | M22: i | N22: ☑ | Q22: ☑ | S22: o | U22: o | Z22: o | AA22: o | AB22: o | AC22: o | AD22: o
C23: Tolaram | G23: i | H23: o | I23: o | J23: o | L23: o | M23: X | N23: ☑ | Q23: ☑ | U23: o | AA23: o | AM23: o
C24: Harshad CHSL | L24: o | M24: i | N24: o | P24: o | T24: o | W24: o | AF24: o | AN24: x | AP24: o | AQ24: o | AS24: o
C25: Redstone, Juhu | F25: x | G25: x | K25: x | L25: i | M25: i | N25: o | O25: o | P25: ☑ | Q25: o | V25: i | X25: o | AD25: o | AO25: o | AS25: o | BD25: o | BE25: o
C26: ARC - Goregaon | N26: o | Q26: x | T26: o | Z26: o | AB26: o | AC26: o | BC26: o | BD26: o
C27: Labh Niwas & Subh Niwas CHSL
C28: Laxminarayan & Devlok | AO28: o
C29: Bezzola, Chembur | N29: o | P29: X | AG29: o
C30: Nalanda Malad | T30: o | V30: o
C31: Mahindra Nagar | I31: o | K31: S | M31: S
C32: Manish Nagar
C33: Shree Ganesh Krupa | AV33: o | AY33: o | BA33: o
C34: Thane VKG - JV/JD | H34: S | I34: S | J34: S | K34: S
C35: Triveni - Mulund | J35: S | L35: S | X35: o | AE35: o | AF35: o | AJ35: o | AK35: o | AR35: o | AS35: o | AU35: o | AZ35: o
C36: VKG, Kandivali | N36: o
C37: Brindaban Dham
C38: Bara Chawl | P38: o | X38: o | AK38: o | AT38: o
C39: BKC Kapadia - VKG - JV/JD | H39: S | I39: S | J39: S | M39: S
C40: Bara Chawl + Topowan | P40: o | AA40: o | AT40: X
C41: Himalaya
C42: Narayana Guru CHS | AB42: o | AF42: X | AW42: o | AX42: o
C43: Subash Nagar (1&30) | AW43: o
C44: 2 Acre Kalina | D44: Shubham | E44: Vineet | K44: o | M44: S | AG44: o
C45: Lokhandwala Cluster | I45: o
C46: Champak | M46: S
C47: Maker Mahal | F47: i | M47: S
C48: VIP | W48: o | AS48: o
C49: Asian Chemical Outright | K49: X | M49: x | R49: o | S49: o | AB49: o | AG49: o | BD49: o | BL49: o
C50: Karnatak CHSL, Matunga | I50: o | J50: o | L50: o | M50: o | N50: o | P50: ☑ | Q50: o | BF50: o | BG50: o | BH50: o | BI50: o
C51: Usha | P51: ☑ | BJ51: o | BK51: o
C52: LIC Colony | J52: o | L52: o | M52: o | N52: ☑ | P52: o | Q52: o | U52: o | W52: o | AS52: ☑ | BH52: o
C53: Om Niwas | AN53: ☑
C54: GTB Nagar, Sion | H54: S | L54: o | Q54: o | AA54: o | BI54: o
C55: LBS Marg - Outright | K55: s | L55: o | M55: s | Y55: s | AG55: s
C56: Q-Group Thane | L56: o
C57: Kalher | H57: o | L57: o
C58: Ram Laxman Kutir | L58: o | N58: o | BL58: o
C59: Vikhroli Land
C60: Empire Guide, Malabar Hills | I60: o | BF60: o | BM60: o
C61: Pestom Sagar, Chembur | AW61: s
C62: Powai Open Land | H62: o | BG62: o
C63: Khar Cluster | BN63: o
C64: Open Plot, LBS Marg | F64: x | L64: o | M64: o | Y64: x | AG64: o | AK64: o | BG64: x | BO64: o
C65: Girgaum Plot | M65: o | P65: o | AA65: o | BF65: o
B75: Opps list
B76: Type
B77: PMC | C77: Bandstand apartments
B78: PMC | C78: Jaywant
B79: PMC | C79: Greenfield - 3
B80: PMC | C80: Greenfield - Namaskar
B81: PMC | C81: Greenfield - Swagat
B82: PMC | C82: Sunder
B83: DR | C83: Vijay Bharat
B84: PMC | C84: Nav Jivan
B85: PMC | C85: Avanti - Dadar
B86: PMC | C86: Ratan Nagar - AG
B89: Won List
B90: Type
B91: PMC | C91: Ayodhaya
B92: PMC | C92: Triveni
B93: PMC | C93: NJD
B94: PMC | C94: Dudhsagar
B95: PMC | C95: Rajiv
B96: PMC | C96: Divya Jyot
B97: PMC | C97: Prahlad
B98: PMC | C98: Lokhandwala
B99: PMC | C99: Manish Nagar
B100: PMC | C100: Gloma

Sheet List of Active Developers 
B1: List of Developers | C1: Email ID
A2: 1 | B2: Runwal - Sandeep
A3: 2 | B3: Runwal - Subodh
A4: 3 | B4: Sobha
A5: 4 | B5: L&T
A6: 5 | B6: Mahindra
A7: 6 | B7: HOH
A8: 7 | B8: Kolte Patil
A9: 8 | B9: Sattva
A10: 9 | B10: Ramky
A11: 10 | B11: Crest
A12: 11 | B12: Prescon
A13: 12 | B13: NCC
... A38: 37 | B38: NESCO
A39: 38
A40: 39
A41: 40
A42: 41

Sheet Sheet1
B2: Propetry | C2: Location | D2: Rescource | E2: Status | F2: SPOC / Agent | G2: Type 3 | H2: Location | I2: Plot size (sq.m.) | J2: FSI Potential | K2: Regulation Proposed
A3: =A2+1 -> 1 | B3: Borla | C3: Chembur | D3: Shali | E3: Active | F3: Ashok | G3: Redevelopment | H3: Maps | I3: 13890.2 | J3: 5.4 | K3: 33(9)
A4: =A3+1 -> 2 | B4: 2 Acre Kalina | C4: Bandra East | D4: SP | E4: Slow cooking | F4: Jejesh | G4: Outright | H4: Maps | I4: 9991 | J4: 6.75 | K4: 33(19)
A5: =A4+1 -> 3 | B5: Tolaram | C5: Chembur | D5: Shali/SP | E5: Hot | F5: Adinath | G5: Redevelopment | H5: Maps | I5: 18618 | J5: 4.79 | K5: 33(9)
A6: =A5+1 -> 4 | B6: Nityanand Bagh | C6: Chembur | D6: Shali/SSD | E6: Hot | F6: Mr. Thakur (Mahendra Kasture) | G6: Redevelopment | H6: Maps | I6: 15348 | J6: 5.4 | K6: 33(9)
A7: =A6+1 -> 5 | B7: Bezzola Complex | C7: Chembur | D7: SP | E7: Dropped | F7: Adinath | G7: Redevelopment | H7: Maps | I7: 11502.2 | J7: 6.75 | K7: 33(19)
A8: =A7+1 -> 6 | B8: Sumer Nagar | C8: Borivali West | D8: SP | E8: Active | F8: Chandrashekhar | G8: Redevelopment | H8: Maps | I8: 12662 | J8: 5.4 | K8: 33(9)
A9: =A8+1 -> 7 | B9: Ambedkar Nagar CHSL | C9: Worli | D9: Vineet | E9: Active | F9: Agrawals | G9: Redevelopment | H9: Maps | I9: 9311 | J9: 5.4 | K9: 33(5)
A10: =A9+1 -> 8 | B10: Manish Nagar | C10: Andheri W | D10: SP/Sagar | E10: Active | F10: Jayantilal Patel | G10: Redevelopment | H10: Maps | I10: 10217 | J10: 5.4 | K10: 33(9)
A11: =A10+1 -> 9 | B11: Khajuria Nagar | C11: Kandivali West | D11: Sahil | E11: Active | F11: Vijay Mundra | G11: Redevelopment | H11: Maps | I11: 11895.33 | J11: 4.34 | K11: 33(9)
A12: =A11+1 -> 10 | B12: Shree ram | C12: Andheri W | D12: SP | E12: Active | F12: AV Rajan | G12: Redevelopment | H12: Map | I12: 13882 | J12: 3.3 | K12: 33(7B)
A13: =A12+1 -> 11 | B13: Shree Niketan | C13: Santacruz W | D13: Shali | E13: Active | F13: Sameer Sata | G13: Redevelopment | H13: Maps | I13: 2416 | J13: 5.4 | K13: 33(11)
A14: =A13+1 -> 12 | B14: Woodstock CHSL | C14: Versova | D14: Vru | E14: Slow cooking | F14: - | G14: Redevelopment | H14: Maps | I14: 6653 | J14: 5.1 | K14: 33(9)
... A17: =A16+1 -> 15 | B17: Karnatak CHSL | C17: Matunga | D17: Vineet | E17: Active | F17: Ramesh | G17: Redevelopment | H17: Maps | I17: 5850 | J17: 5.4 | K17: 33(9)
A18: =A17+1 -> 16 | B18: LIC Colony | C18: Mulund West | D18: Sagar | E18: Hot | G18: Redevelopment | H18: Maps | I18: 10715 | J18: 4.7 | K18: 33(9)
A19: =A18+1 -> 17 | B19: Maker Mahal | C19: Bandra West | D19: SP | E19: Hot | G19: Outright | H19: ='[1]Reg. 33(11)'!F37 -> m | I19: 2025.9 | J19: 5.4 | K19: 30(A) + 20(B)
A20: =A19+1 -> 18 | B20: Rajendra Park CHS | C20: Goregaon West | D20: Vineet | E20: Active | F20: Sonali RERA | G20: Redevelopment | H20: Maps | I20: 6777.82 | J20: 5.4 | K20: 33(9)
A21: =A20+1 -> 19 | B21: Ayodhya CHSL | C21: Lower Parel | D21: Vineet | E21: Active | F21: Stanley & Sameer Kadri | G21: Redevelopment | H21: Maps | I21: 4278.91 | J21: 7.02 | K21: 33(9)
A22: =A21+1 -> 20 | B22: Nalanda CHSL | C22: Malad | D22: Sagar | E22: Active | G22: Redevelopment | H22: Maps | I22: 6680 | J22: 5.18 | K22: 33(9)
A23: =A22+1 -> 21 | B23: Dadar Avanti CHSL | C23: Dadar W | D23: Vineet | E23: Active | G23: Redevelopment | H23: Maps | I23: 4801 | J23: 5.4 | K23: 33(9)
A24: =A23+1 -> 22 | B24: Gandhi Market | C24: Sion | E24: Dropped | F24: BL Pandey | G24: Redevelopment | I24: 5894.7 | J24: 6.26 | K24: 33(9)
A25: =A24+1 -> 23 | B25: Himalaya | C25: Worli | D25: Vineet | E25: Active | F25: 0 | G25: Redevelopment | H25: Map | I25: 2661 | J25: 5.4 | K25: 33(20B)
A26: =A25+1 -> 24 | B26: Narayana Guru CHS | C26: Chembur | E26: Dropped | F26: Mr. Thakur (Mahendra Kasture) | G26: Redevelopment | H26: MAPS | I26: 9486 | J26: 4.94 | K26: 33(9)
A27: =A26+1 -> 25 | B27: Asia Chemical Works | C27: Andheri East | D27: Vineet | E27: Active | F27: Vinay | G27: Ouright | H27: Maps | I27: 3644 | J27: 4.05 | K27: 33(11)
A28: =A27+1 -> 26 | B28: Prahlad CHSL | C28: Santacruz | D28: Vineet | E28: Active | F28: Prem | G28: Redevelopment | H28: Maps | I28: 2418.71 | J28: 5.4 | K28: 33(11)
A29: =A28+1 -> 27 | B29: Jasmine & Moonira lodge | C29: Colaba Causeway | D29: Sagar | E29: Active | F29: Vijay Mundra & Naveen Parikh | G29: JV/JD | H29: Maps | I29: 1270.91 | J29: 5.4 | K29: 33(7) + 33(12B)
A30: =A29+1 -> 28 | B30: New Jal Darshan | C30: Bandra W | E30: Won | F30: Sachin Agrawal | G30: Redevelopment | H30: Maps | I30: 2053.2 | J30: 4.05 | K30: 33(11)
A31: =A30+1 -> 29 | B31: Aangan & Maryland | C31: Sion | D31: Vineet | E31: Slow cooking | F31: Sachin Agrawal | G31: Redevelopment | H31: Map | I31: 3508 | J31: 5.4 | K31: 33(11)
A32: =A31+1 -> 30 | B32: Labh Niwas & Subh Niwas CHSL | C32: Ghatkopar | D32: SP | E32: Slow Cooking | F32: Ashok Borana | G32: Redevelopment | I32: 1899.5 | J32: 4.05 | K32: 33(19)
A33: =A32+1 -> 31 | B33: Laxminarayan & Devlok & Devdeep (new) | C33: Santacruz W | D33: Vineet | E33: Active | F33: Sameer Sata | G33: Redevelopment | H33: Maps | I33: 2045.85 | J33: 2.97 | K33: 33(7B)
A34: =A33+1 -> 32 | B34: VIP | C34: Vile Parle East | D34: Vineet | E34: Hot | G34: Redevelopment | H34: Maps | I34: 909.2 | J34: 3.04 | K34: 30(A) + 20(B)
A35: =A34+1 -> 33 | B35: Bandstand Apartments | C35: Bandra | D35: Sahil | E35: To be figured | G35: Redevelopment | I35: 1749
A36: =A35+1 -> 34 | B36: Jayshree Apartments | C36: Worli | D36: Vineet | E36: Active | F36: Cheetak | G36: JV/JD | H36: Maps | I36: 1672 | J36: 5.4 | K36: 30(A)+20(B)
A37: =A36+1 -> 35 | B37: Lokhandwala Cluster | C37: Andheri W | D37: Shali | E37: Active | F37: Ashok Borana | G37: Redevelopment | I37: -
A38: =A37+1 -> 36 | B38: New Haven | C38: Andheri W | D38: SP | E38: Active | F38: Vinay | I38: 2252
A39: =A38+1 -> 37 | B39: Om Niwas | C39: Kurla | D39: Vineet | E39: Active | F39: Ashok Borana | G39: outright | I39: 2885 | J39: 5.4 | K39: 30(A)+20(B)
A40: =A39+1 -> 38 | B40: Rajiv CHS | C40: Bandra East | D40: Sagar | E40: Active | G40: Redevelopment | H40: Maps | I40: 1787 | K40: 33(7B) +20(B)
A41: =A40+1 -> 39 | B41: Goshala road Cluster | C41: Mulund W | D41: SP | E41: Won | F41: Ashok Borana | G41: Redevelopment | I41: 3394.3 | J41: 5.4 | K41: 33(7B) + 33(20B)
A42: =A41+1 -> 40 | B42: Ram Laxman Kutir | C42: Andehri | D42: Sagar | E42: Active | G42: Redevelopment | H42: Maps | I42: 5099 | J42: 4.05 | K42: 33(11)
A43: =A42+1 -> 41 | B43: Redstone | C43: Juhu | D43: Vineet | E43: Active | F43: Himanshu | G43: Redevelopment | I43: -
A44: =A43+1 -> 42 | B44: Dominic Condiminum | C44: Bandra | E44: Dropped | F44: 0 | G44: Redevelopment | I44: 516.7 | J44: 4.05 | K44: 33(7B )+ 33(12B)
A45: =A44+1 -> 43 | B45: Sudhir Complex | C45: Mulund | D45: Sagar | E45: Active | G45: Redevelopment | I45: 5672 | J45: 5.4 | K45: 33(11)
A46: =A45+1 -> 44 | B46: Sunder | C46: Chembur | D46: Sagar | E46: Active | G46: Redevelopment | H46: Maps | I46: 5167 | J46: 5.4 | K46: 33(11)
A47: =A46+1 -> 45 | B47: Usha Villa | C47: Santacruz West | D47: Vineet | E47: Active | G47: JV/JD | H47: Maps | I47: 1026 | J47: 5.4 | K47: 33(11)
A48: =A47+1 -> 46 | B48: Kailash Cottage & Shamdham Building | C48: Sion | E48: Dropped | G48: Redevelopment | H48: Maps | I48: 984 | J48: 6.34 | K48: 33(7)
A49: =A48+1 -> 47 | B49: Samruddhi CHSL | C49: Mulund East | D49: Vineet | G49: Redevelopment | I49: 1005 | J49: 5.4 | K49: 33(7B) +(20B)
A50: =A49+1 -> 48 | B50: Lal Bahadur Shastri Road | C50: Vikhroli West | D50: Sagar | E50: Active | H50: Maps | I50: 3652
A51: =A50+1 -> 49 | B51: 17Acre Versova | C51: Versova | D51: Sahil | E51: Slow cooking | F51: Sujeet | G51: Outright | I51: 68796.559
A52: =A51+1 -> 50 | B52: Cama Industrial Estate, Goregaon | C52: Goregaon | D52: Vineet | E52: Active | H52: Maps | I52: 2111.76 | J52: 5.4 | K52: 33(19)
A53: =A52+1 -> 51 | B53: Alpa | C53: Vile Parle | E53: Dropped
A54: =A53+1 -> 52 | B54: Arya Nagar | C54: Tardeo | E54: Dropped | G54: Redevelopment
A55: =A54+1 -> 53 | B55: Ashok Nagar | C55: Mulund W | E55: Dropped | F55: Ashok Borana | G55: Redevelopment
A56: =A55+1 -> 54 | B56: Bandra Beach View | C56: Bandra W | E56: Dropped | F56: Sachin Agrawal | G56: Redevelopment
A57: =A56+1 -> 55 | B57: Morumal Mansion CHSL, Khar | C57: Khar West | D57: SP | E57: Cold | F57: Dinesh | G57: JV/JD | H57: Maps | I57: 915
A58: =A57+1 -> 56 | B58: Bangunagar | D58: Vineet | E58: Slow Cooking | I58: -
A59: =A58+1 -> 57 | B59: Bayview Apartments | C59: Bandra W | E59: Dropped | F59: Naresh Rohira | G59: Redevelopment | I59: 1336
A60: =A59+1 -> 58 | B60: BKC Kapadia - VKG - JV/JD | C60: BKC | D60: Vru | E60: Cold | G60: Redevelopment | I60: 40186 | K60: 33(9)
A61: =A60+1 -> 59 | B61: Boricha Chawl | C61: Vile Parle | E61: Dropped | F61: 0 | G61: Redevelopment
A62: =A61+1 -> 60 | B62: Botadkarwadi | C62: Prabhadevi | E62: Dropped | F62: Sachin Agrawal | G62: Redevelopment | I62: 4153
A63: =A62+1 -> 61 | B63: Brookhaven | E63: Dropped | F63: 0 | G63: Redevelopment
A64: =A63+1 -> 62 | B64: Q Group, Thane | D64: SP | E64: Active | I64: -
A65: =A64+1 -> 63 | B65: Champak | C65: Andheri West | E65: Dropped | G65: Outright | H65: Maps | I65: 9402
A66: =A65+1 -> 64 | B66: Charkup plot | C66: Kandivali west | E66: Dropped | F66: Ashok Borana | G66: Redevelopment
A67: =A66+1 -> 65 | B67: Chintamani CHS | C67: Lalbaug / Byculla | E67: Dropped | F67: Stanley | G67: Redevelopment
A68: =A67+1 -> 66 | B68: Deora Building | C68: Malad East | E68: Dropped
A69: =A68+1 -> 67 | B69: D'silva | C69: Ghatkopar | D69: Vru | E69: Cold | G69: Redevelopment | I69: -
A70: =A69+1 -> 68 | B70: Dudh Sagar CHS | C70: Goregaon E | D70: SP | E70: Won | F70: Ramesh Chettiar | G70: Redevelopment | I70: 20000 | J70: =INDEX('Opps combined list'!$1:$1048576,MATCH('Data Dump'!$B20,'Opps combined list'!$C:$C,0),MATCH('Data Dump'!I$4,'Opps combined list'!$4:$4,0)) -> #N/A
A71: =A70+1 -> 69 | B71: Empire Guide | C71: Malabar hills | E71: Dropped | F71: NewsPaper Tender | G71: Redevelopment | I71: 4006
A72: =A71+1 -> 70 | B72: Evershine Apartments | C72: Versova | E72: Dropped | F72: Mahendra Kasture | G72: Redevelopment | I72: 7311
A73: =A72+1 -> 71 | B73: Fakruddin | C73: Kalyan | E73: Dropped
A74: =A73+1 -> 72 | B74: Flower Queen | E74: Dropped | F74: 0 | G74: Redevelopment
A75: =A74+1 -> 73 | B75: Forjett | C75: Lower Parel | E75: Dropped | F75: Agarwals | G75: Redevelopment | I75: 4942.16
A76: =A75+1 -> 74 | B76: Gita | C76: Sion | E76: Development Arm | F76: 0 | G76: Redevelopment | I76: 590
A77: =A76+1 -> 75 | B77: Global E- Services Pvt. Ltd. | C77: Kandivali E | E77: Dropped | F77: Colliers | G77: Outright | I77: 23274
A78: =A77+1 -> 76 | B78: Gokul Regency one | C78: 0 | E78: Dropped | F78: 0 | G78: Redevelopment | I78: 0
A79: =A78+1 -> 77 | B79: Govardhan Nagar | C79: Mulund W | E79: Dropped | F79: Sagar Salian | G79: Redevelopment | I79: 30379
A80: =A79+1 -> 78 | B80: Napean House | C80: Malabar hills | D80: Sahil | E80: Active | F80: Sagar Salian | G80: Outright | H80: Maps | I80: 2006 | J80: 5.4 | K80: 33(7) + 20(B)
A81: =A80+1 -> 79 | B81: Greelawns | C81: Worli Sea Face | E81: Dropped | F81: Agarwals | G81: Outright
A82: =A81+1 -> 80 | B82: Green Gates Apartments | C82: Bandra W | E82: Dropped | F82: AOS | G82: Redevelopment
A83: =A82+1 -> 81 | B83: Green Parks | E83: Dropped | F83: 0 | G83: Redevelopment
A84: =A83+1 -> 82 | B84: Hemu Kalani | C84: navi Mumbai | E84: Won | F84: MS/Agarwals | G84: Redevelopment | I84: 2971 | K84: 33(10)&33(11)
A85: =A84+1 -> 83 | B85: Himachal House | C85: Prabhadevi | E85: Slow Cooking | I85: -
A86: =A85+1 -> 84 | B86: Hormuzd Apartments | C86: Malabar hills | E86: Dropped | F86: Agarwals | G86: Redevelopment
A87: =A86+1 -> 85 | B87: Jagat Vidhya | C87: BKC | E87: Dropped
A88: =A87+1 -> 86 | B88: Jayshree SBI | C88: Worli | E88: Dropped | F88: Chetan | G88: Outright
A89: =A88+1 -> 87 | B89: Vikhroli Open Plot | C89: Vikhroli East | E89: Active | G89: Outright | H89: Maps | I89: 23284 | J89: 4.39 | K89: 30 (A) + AR
A90: =A89+1 -> 88 | B90: Jeeta Bungalow | C90: Juhu | E90: Dropped | F90: Sameer Sata | G90: Outright / JV | I90: 905
A91: =A90+1 -> 89 | B91: Mehta House Bungalow | C91: Juhu | E91: Dropped | G91: Outright | H91: Maps | I91: 940 | J91: 3.54 | K91: 30(A) + 20(B)
A92: =A91+1 -> 90 | B92: Jui Nagar | C92: Navi Mumbai | E92: Dropped | F92: 0 | G92: Redevelopment | I92: 3100
A93: =A92+1 -> 91 | B93: Mahindra Nagar | C93: Malad E | D93: SP | E93: Active | F93: Vijay Mundra | G93: Redevelopment | H93: Maps | I93: 58367 | J93: 5.4 | K93: 33(9)
A94: =A93+1 -> 92 | B94: Kalbadevi Redev | C94: Kalbadevi | E94: Dropped | F94: Pooja | G94: Redevelopment | I94: 4076
A95: =A94+1 -> 93 | B95: Kanamwar Nagar | C95: Vikhroli | E95: Dropped
A96: =A95+1 -> 94 | B96: Khandke Cluster | C96: Dadar W | E96: Dropped | F96: Mahendra Kasture | G96: Redevelopment | I96: 0
A97: =A96+1 -> 95 | B97: King Acre | C97: Santacruz | E97: Dropped | F97: Sachin Agrawal | G97: Redevelopment | I97: 3500
A98: =A97+1 -> 96 | B98: King of Suburbs | C98: Khar | E98: Cold | F98: AOS | G98: Redevelopment | I98: -
A99: =A98+1 -> 97 | B99: Kiran Villa | C99: Peddar Road | E99: Dropped | F99: Colliers | G99: Redevelopment | I99: 1787
A100: =A99+1 -> 98 | B100: Kishori Court | C100: Worli Sea Face | E100: Dropped | F100: BL Pandey | G100: Outright | I100: 0
A101: =A100+1 -> 99 | B101: Kitan apartments | C101: Matunga East | E101: Dropped | F101: BL Pandey | G101: Redevelopment | I101: 0
A102: =A101+1 -> 100 | B102: Kora Kendra Hall | C102: Borivali W | E102: Dropped | F102: Vijay Mundra | G102: Outright / JV | I102: 18296
A103: =A102+1 -> 101 | B103: Land Breeze, Pali hill | C103: Bandra | E103: Dropped | F103: Prem/Sachin | G103: Redevelopment | I103: 0
...

Sheet Hot Tracker
G1: x | H1: o | I1: ☑ | J1: S | K1: i
G2: Declined | H2: Sent | I2: EOI Rec. | J2: To be Sent | K2: interested
B4: Pipeline
B5: Status | D5: PoC - 1 | E5: PoC - 2 | F5: Runwal - Sandeep | G5: Runwal - Subodh | H5: Sobha | I5: L&T | J5: Mahindra | K5: HOH | L5: Kolte Patil | M5: Sattva | N5: Ramky | O5: Crest | P5: Prescon | Q5: NCC | R5: Sunteck | S5: VKG | T5: Kabra | U5: Raymond | V5: SKS Anchor Point | W5: Moongipa | X5: Kanakia | Y5: H.rishabhraj | Z5: Aditya Birla | AA5: Veena | AB5: DGS | AC5: K Raheja | AD5: Matrix | AE5: Kohinoor | AF5: Greenscape | AG5: Sonal | AH5: Q group | AI5: Raheja Homes | AJ5: Silver | AK5: Bluekey realty | AL5: Arkade | AM5: Lloyds | AN5: Sugee | AO5: Aditya Raj | AP5: Pushpa Raj | AQ5: Mass Group | AR5: Sumukha | AS5: Arth | AT5: Sai | AU5: Om | AV5: Mohite | AW5: Tater World | AX5: AVSN | AY5: B-right | AZ5: Puri Creators | BA5: Paradigm | BB5: Maniar | BC5: Agami | BD5: K Nagpal | BE5: Piramal | BF5: Kalpataru | BG5: Sheth | BH5: Tribeca | BI5: Supreme | BJ5: Woodstock
C6: Anand Nagar Santacruz | F6: =INDEX('Proposal Tracker'!$1:$1048576,MATCH('Hot Tracker'!$C6,'Proposal Tracker'!$C:$C,0),MATCH('Hot Tracker'!F$5,'Proposal Tracker'!$4:$4,0)) -> 0 | G6: =INDEX('Proposal Tracker'!$1:$1048576,MATCH('Hot Tracker'!$C6,'Proposal Tracker'!$C:$C,0),MATCH('Hot Tracker'!G$5,'Proposal Tracker'!$4:$4,0)) -> 0 | H6: =INDEX('Proposal Tracker'!$1:$1048576,MATCH('Hot Tracker'!$C6,'Proposal Tracker'!$C:$C,0),MATCH('Hot Tracker'!H$5,'Proposal Tracker'!$4:$4,0)) -> 0 | I6: =INDEX('Proposal Tracker'!$1:$1048576,MATCH('Hot Tracker'!$C6,'Proposal Tracker'!$C:$C,0),MATCH('Hot Tracker'!I$5,'Proposal Tracker'!$4:$4,0)) -> 0 | J6: =INDEX('Proposal Tracker'!$1:$1048576,MATCH('Hot Tracker'!$C6,'Proposal Tracker'!$C:$C,0),MATCH('Hot Tracker'!J$5,'Proposal Tracker'!$4:$4,0)) -> 0 | K6: =INDEX('Proposal Tracker'!$1:$1048576,MATCH('Hot Tracker'!$C6,'Proposal Tracker'!$C:$C,0),MATCH('Hot Tracker'!K$5,'Proposal Tracker'!$4:$4,0)) -> 0 | L6: =INDEX('Proposal Tracker'!$1:$1048576,MATCH('Hot Tracker'!$C6,'Proposal Tracker'!$C:$C,0),MATCH('Hot Tracker'!L$5,'Proposal Tracker'!$4:$4,0)) -> 0 | M6: =INDEX('Proposal Tracker'!$1:$1048576,MATCH('Hot Tracker'!$C6,'Proposal Tracker'!$C:$C,0),MATCH('Hot Tracker'!M$5,'Proposal Tracker'!$4:$4,0)) -> 0 | ... BJ6: =INDEX('Proposal Tracker'!$1:$1048576,MATCH('Hot Tracker'!$C6,'Proposal Tracker'!$C:$C,0),MATCH('Hot Tracker'!BJ$5,'Proposal Tracker'!$4:$4,0)) -> 0
C7: Borla | F7: =INDEX('Proposal Tracker'!$1:$1048576,MATCH('Hot Tracker'!$C7,'Proposal Tracker'!$C:$C,0),MATCH('Hot Tracker'!F$5,'Proposal Tracker'!$4:$4,0)) -> 0 | G7: =INDEX('Proposal Tracker'!$1:$1048576,MATCH('Hot Tracker'!$C7,'Proposal Tracker'!$C:$C,0),MATCH('Hot Tracker'!G$5,'Proposal Tracker'!$4:$4,0)) -> 0 | H7: =INDEX('Proposal Tracker'!$1:$1048576,MATCH('Hot Tracker'!$C7,'Proposal Tracker'!$C:$C,0),MATCH('Hot Tracker'!H$5,'Proposal Tracker'!$4:$4,0)) -> ☑ | I7: =INDEX('Proposal Tracker'!$1:$1048576,MATCH('Hot Tracker'!$C7,'Proposal Tracker'!$C:$C,0),MATCH('Hot Tracker'!I$5,'Proposal Tracker'!$4:$4,0)) -> o | J7: =INDEX('Proposal Tracker'!$1:$1048576,MATCH('Hot Tracker'!$C7,'Proposal Tracker'!$C:$C,0),MATCH('Hot Tracker'!J$5,'Proposal Tracker'!$4:$4,0)) -> o | K7: =INDEX('Proposal Tracker'!$1:$1048576,MATCH('Hot Tracker'!$C7,'Proposal Tracker'!$C:$C,0),MATCH('Hot Tracker'!K$5,'Proposal Tracker'!$4:$4,0)) -> X | L7: =INDEX('Proposal Tracker'!$1:$1048576,MATCH('Hot Tracker'!$C7,'Proposal Tracker'!$C:$C,0),MATCH('Hot Tracker'!L$5,'Proposal Tracker'!$4:$4,0)) -> X | M7: =INDEX('Proposal Tracker'!$1:$1048576,MATCH('Hot Tracker'!$C7,'Proposal Tracker'!$C:$C,0),MATCH('Hot Tracker'!M$5,'Proposal Tracker'!$4:$4,0)) -> X | ... BJ7: =INDEX('Proposal Tracker'!$1:$1048576,MATCH('Hot Tracker'!$C7,'Proposal Tracker'!$C:$C,0),MATCH('Hot Tracker'!BJ$5,'Proposal Tracker'!$4:$4,0)) -> 0
C8: Khajuria Nagar | F8: =INDEX('Proposal Tracker'!$1:$1048576,MATCH('Hot Tracker'!$C8,'Proposal Tracker'!$C:$C,0),MATCH('Hot Tracker'!F$5,'Proposal Tracker'!$4:$4,0)) -> o | G8: =INDEX('Proposal Tracker'!$1:$1048576,MATCH('Hot Tracker'!$C8,'Proposal Tracker'!$C:$C,0),MATCH('Hot Tracker'!G$5,'Proposal Tracker'!$4:$4,0)) -> o | H8: =INDEX('Proposal Tracker'!$1:$1048576,MATCH('Hot Tracker'!$C8,'Proposal Tracker'!$C:$C,0),MATCH('Hot Tracker'!H$5,'Proposal Tracker'!$4:$4,0)) -> 0 | I8: =INDEX('Proposal Tracker'!$1:$1048576,MATCH('Hot Tracker'!$C8,'Proposal Tracker'!$C:$C,0),MATCH('Hot Tracker'!I$5,'Proposal Tracker'!$4:$4,0)) -> S | J8: =INDEX('Proposal Tracker'!$1:$1048576,MATCH('Hot Tracker'!$C8,'Proposal Tracker'!$C:$C,0),MATCH('Hot Tracker'!J$5,'Proposal Tracker'!$4:$4,0)) -> S | K8: =INDEX('Proposal Tracker'!$1:$1048576,MATCH('Hot Tracker'!$C8,'Proposal Tracker'!$C:$C,0),MATCH('Hot Tracker'!K$5,'Proposal Tracker'!$4:$4,0)) -> S | L8: =INDEX('Proposal Tracker'!$1:$1048576,MATCH('Hot Tracker'!$C8,'Proposal Tracker'!$C:$C,0),MATCH('Hot Tracker'!L$5,'Proposal Tracker'!$4:$4,0)) -> S | M8: =INDEX('Proposal Tracker'!$1:$1048576,MATCH('Hot Tracker'!$C8,'Proposal Tracker'!$C:$C,0),MATCH('Hot Tracker'!M$5,'Proposal Tracker'!$4:$4,0)) -> 0 | ... BJ8: =INDEX('Proposal Tracker'!$1:$1048576,MATCH('Hot Tracker'!$C8,'Proposal Tracker'!$C:$C,0),MATCH('Hot Tracker'!BJ$5,'Proposal Tracker'!$4:$4,0)) -> 0
C9: New Jal Darshan | F9: =INDEX('Proposal Tracker'!$1:$1048576,MATCH('Hot Tracker'!$C9,'Proposal Tracker'!$C:$C,0),MATCH('Hot Tracker'!F$5,'Proposal Tracker'!$4:$4,0)) -> 0 | G9: =INDEX('Proposal Tracker'!$1:$1048576,MATCH('Hot Tracker'!$C9,'Proposal Tracker'!$C:$C,0),MATCH('Hot Tracker'!G$5,'Proposal Tracker'!$4:$4,0)) -> i | H9: =INDEX('Proposal Tracker'!$1:$1048576,MATCH('Hot Tracker'!$C9,'Proposal Tracker'!$C:$C,0),MATCH('Hot Tracker'!H$5,'Proposal Tracker'!$4:$4,0)) -> S | I9: =INDEX('Proposal Tracker'!$1:$1048576,MATCH('Hot Tracker'!$C9,'Proposal Tracker'!$C:$C,0),MATCH('Hot Tracker'!I$5,'Proposal Tracker'!$4:$4,0)) -> o | J9: =INDEX('Proposal Tracker'!$1:$1048576,MATCH('Hot Tracker'!$C9,'Proposal Tracker'!$C:$C,0),MATCH('Hot Tracker'!J$5,'Proposal Tracker'!$4:$4,0)) -> S | K9: =INDEX('Proposal Tracker'!$1:$1048576,MATCH('Hot Tracker'!$C9,'Proposal Tracker'!$C:$C,0),MATCH('Hot Tracker'!K$5,'Proposal Tracker'!$4:$4,0)) -> S | L9: =INDEX('Proposal Tracker'!$1:$1048576,MATCH('Hot Tracker'!$C9,'Proposal Tracker'!$C:$C,0),MATCH('Hot Tracker'!L$5,'Proposal Tracker'!$4:$4,0)) -> S | M9: =INDEX('Proposal Tracker'!$1:$1048576,MATCH('Hot Tracker'!$C9,'Proposal Tracker'!$C:$C,0),MATCH('Hot Tracker'!M$5,'Proposal Tracker'!$4:$4,0)) -> S | ... BJ9: =INDEX('Proposal Tracker'!$1:$1048576,MATCH('Hot Tracker'!$C9,'Proposal Tracker'!$C:$C,0),MATCH('Hot Tracker'!BJ$5,'Proposal Tracker'!$4:$4,0)) -> 0
C10: Nityanand Baug | F10: =INDEX('Proposal Tracker'!$1:$1048576,MATCH('Hot Tracker'!$C10,'Proposal Tracker'!$C:$C,0),MATCH('Hot Tracker'!F$5,'Proposal Tracker'!$4:$4,0)) -> 0 | G10: =INDEX('Proposal Tracker'!$1:$1048576,MATCH('Hot Tracker'!$C10,'Proposal Tracker'!$C:$C,0),MATCH('Hot Tracker'!G$5,'Proposal Tracker'!$4:$4,0)) -> x | H10: =INDEX('Proposal Tracker'!$1:$1048576,MATCH('Hot Tracker'!$C10,'Proposal Tracker'!$C:$C,0),MATCH('Hot Tracker'!H$5,'Proposal Tracker'!$4:$4,0)) -> o | I10: =INDEX('Proposal Tracker'!$1:$1048576,MATCH('Hot Tracker'!$C10,'Proposal Tracker'!$C:$C,0),MATCH('Hot Tracker'!I$5,'Proposal Tracker'!$4:$4,0)) -> o | J10: =INDEX('Proposal Tracker'!$1:$1048576,MATCH('Hot Tracker'!$C10,'Proposal Tracker'!$C:$C,0),MATCH('Hot Tracker'!J$5,'Proposal Tracker'!$4:$4,0)) -> o | K10: =INDEX('Proposal Tracker'!$1:$1048576,MATCH('Hot Tracker'!$C10,'Proposal Tracker'!$C:$C,0),MATCH('Hot Tracker'!K$5,'Proposal Tracker'!$4:$4,0)) -> S | L10: =INDEX('Proposal Tracker'!$1:$1048576,MATCH('Hot Tracker'!$C10,'Proposal Tracker'!$C:$C,0),MATCH('Hot Tracker'!L$5,'Proposal Tracker'!$4:$4,0)) -> i | M10: =INDEX('Proposal Tracker'!$1:$1048576,MATCH('Hot Tracker'!$C10,'Proposal Tracker'!$C:$C,0),MATCH('Hot Tracker'!M$5,'Proposal Tracker'!$4:$4,0)) -> X | ... BJ10: =INDEX('Proposal Tracker'!$1:$1048576,MATCH('Hot Tracker'!$C10,'Proposal Tracker'!$C:$C,0),MATCH('Hot Tracker'!BJ$5,'Proposal Tracker'!$4:$4,0)) -> 0
C11: Prahlad CHSL - Santacurz | F11: =INDEX('Proposal Tracker'!$1:$1048576,MATCH('Hot Tracker'!$C11,'Proposal Tracker'!$C:$C,0),MATCH('Hot Tracker'!F$5,'Proposal Tracker'!$4:$4,0)) -> 0 | G11: =INDEX('Proposal Tracker'!$1:$1048576,MATCH('Hot Tracker'!$C11,'Proposal Tracker'!$C:$C,0),MATCH('Hot Tracker'!G$5,'Proposal Tracker'!$4:$4,0)) -> 0 | H11: =INDEX('Proposal Tracker'!$1:$1048576,MATCH('Hot Tracker'!$C11,'Proposal Tracker'!$C:$C,0),MATCH('Hot Tracker'!H$5,'Proposal Tracker'!$4:$4,0)) -> o | I11: =INDEX('Proposal Tracker'!$1:$1048576,MATCH('Hot Tracker'!$C11,'Proposal Tracker'!$C:$C,0),MATCH('Hot Tracker'!I$5,'Proposal Tracker'!$4:$4,0)) -> o | J11: =INDEX('Proposal Tracker'!$1:$1048576,MATCH('Hot Tracker'!$C11,'Proposal Tracker'!$C:$C,0),MATCH('Hot Tracker'!J$5,'Proposal Tracker'!$4:$4,0)) -> 0 | K11: =INDEX('Proposal Tracker'!$1:$1048576,MATCH('Hot Tracker'!$C11,'Proposal Tracker'!$C:$C,0),MATCH('Hot Tracker'!K$5,'Proposal Tracker'!$4:$4,0)) -> S | L11: =INDEX('Proposal Tracker'!$1:$1048576,MATCH('Hot Tracker'!$C11,'Proposal Tracker'!$C:$C,0),MATCH('Hot Tracker'!L$5,'Proposal Tracker'!$4:$4,0)) -> S | M11: =INDEX('Proposal Tracker'!$1:$1048576,MATCH('Hot Tracker'!$C11,'Proposal Tracker'!$C:$C,0),MATCH('Hot Tracker'!M$5,'Proposal Tracker'!$4:$4,0)) -> S | ... BJ11: =INDEX('Proposal Tracker'!$1:$1048576,MATCH('Hot Tracker'!$C11,'Proposal Tracker'!$C:$C,0),MATCH('Hot Tracker'!BJ$5,'Proposal Tracker'!$4:$4,0)) -> 0
C12: Rajendra Park & Nalanda Mall, Goregaon (West) | F12: =INDEX('Proposal Tracker'!$1:$1048576,MATCH('Hot Tracker'!$C12,'Proposal Tracker'!$C:$C,0),MATCH('Hot Tracker'!F$5,'Proposal Tracker'!$4:$4,0)) -> i | G12: =INDEX('Proposal Tracker'!$1:$1048576,MATCH('Hot Tracker'!$C12,'Proposal Tracker'!$C:$C,0),MATCH('Hot Tracker'!G$5,'Proposal Tracker'!$4:$4,0)) -> o | H12: =INDEX('Proposal Tracker'!$1:$1048576,MATCH('Hot Tracker'!$C12,'Proposal Tracker'!$C:$C,0),MATCH('Hot Tracker'!H$5,'Proposal Tracker'!$4:$4,0)) -> 0 | I12: =INDEX('Proposal Tracker'!$1:$1048576,MATCH('Hot Tracker'!$C12,'Proposal Tracker'!$C:$C,0),MATCH('Hot Tracker'!I$5,'Proposal Tracker'!$4:$4,0)) -> 0 | J12: =INDEX('Proposal Tracker'!$1:$1048576,MATCH('Hot Tracker'!$C12,'Proposal Tracker'!$C:$C,0),MATCH('Hot Tracker'!J$5,'Proposal Tracker'!$4:$4,0)) -> X | K12: =INDEX('Proposal Tracker'!$1:$1048576,MATCH('Hot Tracker'!$C12,'Proposal Tracker'!$C:$C,0),MATCH('Hot Tracker'!K$5,'Proposal Tracker'!$4:$4,0)) -> 0 | L12: =INDEX('Proposal Tracker'!$1:$1048576,MATCH('Hot Tracker'!$C12,'Proposal Tracker'!$C:$C,0),MATCH('Hot Tracker'!L$5,'Proposal Tracker'!$4:$4,0)) -> o | M12: =INDEX('Proposal Tracker'!$1:$1048576,MATCH('Hot Tracker'!$C12,'Proposal Tracker'!$C:$C,0),MATCH('Hot Tracker'!M$5,'Proposal Tracker'!$4:$4,0)) -> x | ... BJ12: =INDEX('Proposal Tracker'!$1:$1048576,MATCH('Hot Tracker'!$C12,'Proposal Tracker'!$C:$C,0),MATCH('Hot Tracker'!BJ$5,'Proposal Tracker'!$4:$4,0)) -> 0
C13: Shree Ram CHSL, Andheri (West) | F13: =INDEX('Proposal Tracker'!$1:$1048576,MATCH('Hot Tracker'!$C13,'Proposal Tracker'!$C:$C,0),MATCH('Hot Tracker'!F$5,'Proposal Tracker'!$4:$4,0)) -> 0 | G13: =INDEX('Proposal Tracker'!$1:$1048576,MATCH('Hot Tracker'!$C13,'Proposal Tracker'!$C:$C,0),MATCH('Hot Tracker'!G$5,'Proposal Tracker'!$4:$4,0)) -> 0 | H13: =INDEX('Proposal Tracker'!$1:$1048576,MATCH('Hot Tracker'!$C13,'Proposal Tracker'!$C:$C,0),MATCH('Hot Tracker'!H$5,'Proposal Tracker'!$4:$4,0)) -> 0 | I13: =INDEX('Proposal Tracker'!$1:$1048576,MATCH('Hot Tracker'!$C13,'Proposal Tracker'!$C:$C,0),MATCH('Hot Tracker'!I$5,'Proposal Tracker'!$4:$4,0)) -> i | J13: =INDEX('Proposal Tracker'!$1:$1048576,MATCH('Hot Tracker'!$C13,'Proposal Tracker'!$C:$C,0),MATCH('Hot Tracker'!J$5,'Proposal Tracker'!$4:$4,0)) -> S | K13: =INDEX('Proposal Tracker'!$1:$1048576,MATCH('Hot Tracker'!$C13,'Proposal Tracker'!$C:$C,0),MATCH('Hot Tracker'!K$5,'Proposal Tracker'!$4:$4,0)) -> ? | L13: =INDEX('Proposal Tracker'!$1:$1048576,MATCH('Hot Tracker'!$C13,'Proposal Tracker'!$C:$C,0),MATCH('Hot Tracker'!L$5,'Proposal Tracker'!$4:$4,0)) -> ☑ | M13: =INDEX('Proposal Tracker'!$1:$1048576,MATCH('Hot Tracker'!$C13,'Proposal Tracker'!$C:$C,0),MATCH('Hot Tracker'!M$5,'Proposal Tracker'!$4:$4,0)) -> i | ... BJ13: =INDEX('Proposal Tracker'!$1:$1048576,MATCH('Hot Tracker'!$C13,'Proposal Tracker'!$C:$C,0),MATCH('Hot Tracker'!BJ$5,'Proposal Tracker'!$4:$4,0)) -> 0
C14: Sumer Nagar | F14: =INDEX('Proposal Tracker'!$1:$1048576,MATCH('Hot Tracker'!$C14,'Proposal Tracker'!$C:$C,0),MATCH('Hot Tracker'!F$5,'Proposal Tracker'!$4:$4,0)) -> i | G14: =INDEX('Proposal Tracker'!$1:$1048576,MATCH('Hot Tracker'!$C14,'Proposal Tracker'!$C:$C,0),MATCH('Hot Tracker'!G$5,'Proposal Tracker'!$4:$4,0)) -> o | H14: =INDEX('Proposal Tracker'!$1:$1048576,MATCH('Hot Tracker'!$C14,'Proposal Tracker'!$C:$C,0),MATCH('Hot Tracker'!H$5,'Proposal Tracker'!$4:$4,0)) -> o | I14: =INDEX('Proposal Tracker'!$1:$1048576,MATCH('Hot Tracker'!$C14,'Proposal Tracker'!$C:$C,0),MATCH('Hot Tracker'!I$5,'Proposal Tracker'!$4:$4,0)) -> o | J14: =INDEX('Proposal Tracker'!$1:$1048576,MATCH('Hot Tracker'!$C14,'Proposal Tracker'!$C:$C,0),MATCH('Hot Tracker'!J$5,'Proposal Tracker'!$4:$4,0)) -> o | K14: =INDEX('Proposal Tracker'!$1:$1048576,MATCH('Hot Tracker'!$C14,'Proposal Tracker'!$C:$C,0),MATCH('Hot Tracker'!K$5,'Proposal Tracker'!$4:$4,0)) -> X | L14: =INDEX('Proposal Tracker'!$1:$1048576,MATCH('Hot Tracker'!$C14,'Proposal Tracker'!$C:$C,0),MATCH('Hot Tracker'!L$5,'Proposal Tracker'!$4:$4,0)) -> o | M14: =INDEX('Proposal Tracker'!$1:$1048576,MATCH('Hot Tracker'!$C14,'Proposal Tracker'!$C:$C,0),MATCH('Hot Tracker'!M$5,'Proposal Tracker'!$4:$4,0)) -> i | ... BJ14: =INDEX('Proposal Tracker'!$1:$1048576,MATCH('Hot Tracker'!$C14,'Proposal Tracker'!$C:$C,0),MATCH('Hot Tracker'!BJ$5,'Proposal Tracker'!$4:$4,0)) -> 0
C15: Tolaram | F15: =INDEX('Proposal Tracker'!$1:$1048576,MATCH('Hot Tracker'!$C15,'Proposal Tracker'!$C:$C,0),MATCH('Hot Tracker'!F$5,'Proposal Tracker'!$4:$4,0)) -> 0 | G15: =INDEX('Proposal Tracker'!$1:$1048576,MATCH('Hot Tracker'!$C15,'Proposal Tracker'!$C:$C,0),MATCH('Hot Tracker'!G$5,'Proposal Tracker'!$4:$4,0)) -> i | H15: =INDEX('Proposal Tracker'!$1:$1048576,MATCH('Hot Tracker'!$C15,'Proposal Tracker'!$C:$C,0),MATCH('Hot Tracker'!H$5,'Proposal Tracker'!$4:$4,0)) -> o | I15: =INDEX('Proposal Tracker'!$1:$1048576,MATCH('Hot Tracker'!$C15,'Proposal Tracker'!$C:$C,0),MATCH('Hot Tracker'!I$5,'Proposal Tracker'!$4:$4,0)) -> o | J15: =INDEX('Proposal Tracker'!$1:$1048576,MATCH('Hot Tracker'!$C15,'Proposal Tracker'!$C:$C,0),MATCH('Hot Tracker'!J$5,'Proposal Tracker'!$4:$4,0)) -> o | K15: =INDEX('Proposal Tracker'!$1:$1048576,MATCH('Hot Tracker'!$C15,'Proposal Tracker'!$C:$C,0),MATCH('Hot Tracker'!K$5,'Proposal Tracker'!$4:$4,0)) -> 0 | L15: =INDEX('Proposal Tracker'!$1:$1048576,MATCH('Hot Tracker'!$C15,'Proposal Tracker'!$C:$C,0),MATCH('Hot Tracker'!L$5,'Proposal Tracker'!$4:$4,0)) -> o | M15: =INDEX('Proposal Tracker'!$1:$1048576,MATCH('Hot Tracker'!$C15,'Proposal Tracker'!$C:$C,0),MATCH('Hot Tracker'!M$5,'Proposal Tracker'!$4:$4,0)) -> X | ... BJ15: =INDEX('Proposal Tracker'!$1:$1048576,MATCH('Hot Tracker'!$C15,'Proposal Tracker'!$C:$C,0),MATCH('Hot Tracker'!BJ$5,'Proposal Tracker'!$4:$4,0)) -> 0
C16: Redstone, Juhu | F16: =INDEX('Proposal Tracker'!$1:$1048576,MATCH('Hot Tracker'!$C16,'Proposal Tracker'!$C:$C,0),MATCH('Hot Tracker'!F$5,'Proposal Tracker'!$4:$4,0)) -> x | G16: =INDEX('Proposal Tracker'!$1:$1048576,MATCH('Hot Tracker'!$C16,'Proposal Tracker'!$C:$C,0),MATCH('Hot Tracker'!G$5,'Proposal Tracker'!$4:$4,0)) -> x | H16: =INDEX('Proposal Tracker'!$1:$1048576,MATCH('Hot Tracker'!$C16,'Proposal Tracker'!$C:$C,0),MATCH('Hot Tracker'!H$5,'Proposal Tracker'!$4:$4,0)) -> 0 | I16: =INDEX('Proposal Tracker'!$1:$1048576,MATCH('Hot Tracker'!$C16,'Proposal Tracker'!$C:$C,0),MATCH('Hot Tracker'!I$5,'Proposal Tracker'!$4:$4,0)) -> 0 | J16: =INDEX('Proposal Tracker'!$1:$1048576,MATCH('Hot Tracker'!$C16,'Proposal Tracker'!$C:$C,0),MATCH('Hot Tracker'!J$5,'Proposal Tracker'!$4:$4,0)) -> 0 | K16: =INDEX('Proposal Tracker'!$1:$1048576,MATCH('Hot Tracker'!$C16,'Proposal Tracker'!$C:$C,0),MATCH('Hot Tracker'!K$5,'Proposal Tracker'!$4:$4,0)) -> x | L16: =INDEX('Proposal Tracker'!$1:$1048576,MATCH('Hot Tracker'!$C16,'Proposal Tracker'!$C:$C,0),MATCH('Hot Tracker'!L$5,'Proposal Tracker'!$4:$4,0)) -> i | M16: =INDEX('Proposal Tracker'!$1:$1048576,MATCH('Hot Tracker'!$C16,'Proposal Tracker'!$C:$C,0),MATCH('Hot Tracker'!M$5,'Proposal Tracker'!$4:$4,0)) -> i | ... BJ16: =INDEX('Proposal Tracker'!$1:$1048576,MATCH('Hot Tracker'!$C16,'Proposal Tracker'!$C:$C,0),MATCH('Hot Tracker'!BJ$5,'Proposal Tracker'!$4:$4,0)) -> 0
C17: Nalanda Malad | F17: =INDEX('Proposal Tracker'!$1:$1048576,MATCH('Hot Tracker'!$C17,'Proposal Tracker'!$C:$C,0),MATCH('Hot Tracker'!F$5,'Proposal Tracker'!$4:$4,0)) -> 0 | G17: =INDEX('Proposal Tracker'!$1:$1048576,MATCH('Hot Tracker'!$C17,'Proposal Tracker'!$C:$C,0),MATCH('Hot Tracker'!G$5,'Proposal Tracker'!$4:$4,0)) -> 0 | H17: =INDEX('Proposal Tracker'!$1:$1048576,MATCH('Hot Tracker'!$C17,'Proposal Tracker'!$C:$C,0),MATCH('Hot Tracker'!H$5,'Proposal Tracker'!$4:$4,0)) -> 0 | I17: =INDEX('Proposal Tracker'!$1:$1048576,MATCH('Hot Tracker'!$C17,'Proposal Tracker'!$C:$C,0),MATCH('Hot Tracker'!I$5,'Proposal Tracker'!$4:$4,0)) -> 0 | J17: =INDEX('Proposal Tracker'!$1:$1048576,MATCH('Hot Tracker'!$C17,'Proposal Tracker'!$C:$C,0),MATCH('Hot Tracker'!J$5,'Proposal Tracker'!$4:$4,0)) -> 0 | K17: =INDEX('Proposal Tracker'!$1:$1048576,MATCH('Hot Tracker'!$C17,'Proposal Tracker'!$C:$C,0),MATCH('Hot Tracker'!K$5,'Proposal Tracker'!$4:$4,0)) -> 0 | L17: =INDEX('Proposal Tracker'!$1:$1048576,MATCH('Hot Tracker'!$C17,'Proposal Tracker'!$C:$C,0),MATCH('Hot Tracker'!L$5,'Proposal Tracker'!$4:$4,0)) -> 0 | M17: =INDEX('Proposal Tracker'!$1:$1048576,MATCH('Hot Tracker'!$C17,'Proposal Tracker'!$C:$C,0),MATCH('Hot Tracker'!M$5,'Proposal Tracker'!$4:$4,0)) -> 0 | ... BJ17: =INDEX('Proposal Tracker'!$1:$1048576,MATCH('Hot Tracker'!$C17,'Proposal Tracker'!$C:$C,0),MATCH('Hot Tracker'!BJ$5,'Proposal Tracker'!$4:$4,0)) -> 0
... C25: LBS Marg - Outright | F25: =INDEX('Proposal Tracker'!$1:$1048576,MATCH('Hot Tracker'!$C25,'Proposal Tracker'!$C:$C,0),MATCH('Hot Tracker'!F$5,'Proposal Tracker'!$4:$4,0)) -> 0 | G25: =INDEX('Proposal Tracker'!$1:$1048576,MATCH('Hot Tracker'!$C25,'Proposal Tracker'!$C:$C,0),MATCH('Hot Tracker'!G$5,'Proposal Tracker'!$4:$4,0)) -> 0 | H25: =INDEX('Proposal Tracker'!$1:$1048576,MATCH('Hot Tracker'!$C25,'Proposal Tracker'!$C:$C,0),MATCH('Hot Tracker'!H$5,'Proposal Tracker'!$4:$4,0)) -> 0 | I25: =INDEX('Proposal Tracker'!$1:$1048576,MATCH('Hot Tracker'!$C25,'Proposal Tracker'!$C:$C,0),MATCH('Hot Tracker'!I$5,'Proposal Tracker'!$4:$4,0)) -> 0 | J25: =INDEX('Proposal Tracker'!$1:$1048576,MATCH('Hot Tracker'!$C25,'Proposal Tracker'!$C:$C,0),MATCH('Hot Tracker'!J$5,'Proposal Tracker'!$4:$4,0)) -> 0 | K25: =INDEX('Proposal Tracker'!$1:$1048576,MATCH('Hot Tracker'!$C25,'Proposal Tracker'!$C:$C,0),MATCH('Hot Tracker'!K$5,'Proposal Tracker'!$4:$4,0)) -> s | L25: =INDEX('Proposal Tracker'!$1:$1048576,MATCH('Hot Tracker'!$C25,'Proposal Tracker'!$C:$C,0),MATCH('Hot Tracker'!L$5,'Proposal Tracker'!$4:$4,0)) -> o | M25: =INDEX('Proposal Tracker'!$1:$1048576,MATCH('Hot Tracker'!$C25,'Proposal Tracker'!$C:$C,0),MATCH('Hot Tracker'!M$5,'Proposal Tracker'!$4:$4,0)) -> s | ... BJ25: =INDEX('Proposal Tracker'!$1:$1048576,MATCH('Hot Tracker'!$C25,'Proposal Tracker'!$C:$C,0),MATCH('Hot Tracker'!BJ$5,'Proposal Tracker'!$4:$4,0)) -> 0
B30: Opps list
B31: Type
B32: PMC | C32: Bandstand apartments
B33: PMC | C33: Jaywant
B34: PMC | C34: Greenfield - 3
B35: PMC | C35: Greenfield - Namaskar
B36: PMC | C36: Greenfield - Swagat
B37: PMC | C37: Sumer Nagar
B46: Won List
B47: Type
B48: PMC | C48: Ayodhaya
B49: PMC | C49: Triveni
B50: PMC | C50: NJD
B51: PMC | C51: Dudhsagar
B52: PMC | C52: Rajiv
B53: PMC | C53: Divya Jyot
B54: PMC | C54: Prahlad
B55: PMC | C55: Lokhandwala
B56: PMC | C56: Manish Nagar

Sheet List of Developers 
A1: Sr. No | B1: Developer | C1: Grade
B2: GRADE - A
A3: 1 | B3: Birla Estates | C3: A
A4: =A3+1 -> 2 | B4: Crest | C4: A
A5: =A4+1 -> 3 | B5: Greenscape | C5: A
A6: =A5+1 -> 4 | B6: House of Hiranandani | C6: A
A7: =A6+1 -> 5 | B7: K raheja Corp | C7: A
A8: =A7+1 -> 6 | B8: Kanakia | C8: A
A9: =A8+1 -> 7 | B9: Kolte patil | C9: A | D9: shadab.siddiqui@koltepatil.com
A10: =A9+1 -> 8 | B10: L&T Realty | C10: A
A11: =A10+1 -> 9 | B11: Mahindra Lifespaces | C11: A | D11: shah.vikhil@mahindra.com
A12: =A11+1 -> 10 | B12: NCC | C12: A | D12: shreya@nccurban.com | E12: jaydeep.roy@nccurban.com
A13: =A12+1 -> 11 | B13: NESCO | C13: A
A14: =A13+1 -> 12 | B14: Ramky | C14: A | D14: bipinpatel@ramky.com
A15: =A14+1 -> 13 | B15: Raymond Realty | C15: A | D15: viral.mehta@raymond.i | E15: rahul.bhangale@raymond.in
A16: =A15+1 -> 14 | B16: Runwal | C16: A | D16: saurabh@runwal.com | E16: sumit.kasat@runwal.com
A17: =A16+1 -> 15 | B17: Sattva | C17: A | D17: amit.patil@sattvagroup.in | E17: sarvesh.agarwal@sattvagroup.in
A18: =A17+1 -> 16 | B18: Sobha | C18: A
A19: =A18+1 -> 17 | B19: Sunteck | C19: A
B20: GRADE - B
A21: =A19+1 -> 18 | B21: Arihant Superstructures | C21: B
A22: =A21+1 -> 19 | B22: Arkade | C22: B
A23: =A22+1 -> 20 | B23: Arth | C23: B
A24: =A23+1 -> 21 | B24: Flora | C24: B
A25: =A24+1 -> 22 | B25: H Rishabhraj | C25: B
A26: =A25+1 -> 23 | B26: L Nagpal | C26: B
A27: =A26+1 -> 24 | B27: Llyods Realty | C27: B
A28: =A27+1 -> 25 | B28: Lotus | C28: B
A29: =A28+1 -> 26 | B29: Mohite | C29: B
A30: =A29+1 -> 27 | B30: Paradigm | C30: B
A31: =A30+1 -> 28 | B31: Prescon | C31: B | D31: vedanshu@prescon.in | E31: chintan.shah@prescon.in
A32: =A31+1 -> 29 | B32: SKS Anchor Point | C32: B
A33: =A32+1 -> 30 | B33: Sugee | C33: B
A34: =A33+1 -> 31 | B34: Veena | C34: B
A35: =A34+1 -> 32 | B35: VKG | C35: B
A36: =A35+1 -> 33 | B36: Vraj | C36: B
B37: GRADE - B
A38: =A36+1 -> 34 | B38: Agarwals | C38: C
A39: =A38+1 -> 35 | B39: AOS | C39: C
A40: =A39+1 -> 36 | B40: AVSN | C40: C
A41: =A40+1 -> 37 | B41: DGS | C41: C
A42: =A41+1 -> 38 | B42: GK Realtors | C42: C
A43: =A42+1 -> 39 | B43: Maniar | C43: C
A44: =A43+1 -> 40 | B44: Moongipa | C44: C | D44: sachit@moongipa.co.in
A45: =A44+1 -> 41 | B45: Radhey | C45: C
A46: =A45+1 -> 42 | B46: Realta Venures | C46: C
A47: =A46+1 -> 43 | B47: Shree Venkateshwara | C47: C
A48: =A47+1 -> 44 | B48: Tater World | C48: C
D49: pranavpathak@gmail.com
D50: chintan.sheth@sheth-realty.com
B52: NEW ENTRANTS
A53: =A51+1 -> 1 | B53: Lamar Realty : Delhi | C53: N | D53: Archit Lochav | E53: l.archit95@gmail.com | I53: 30-50 Cr Initial Investments, No tender
A54: =A53+1 -> 2 | B54: Amaqtra Group | C54: N | D54: Umesh Gupta | E54: umeshgupta@amaatragroup.com | I54: Upto 20 Cr Initial Investments, No tender
A55: =A54+1 -> 3 | B55: AVSN | C55: C

Sheet Opps >1000 cr Topline 
B1: List of Opportunities
B4: Name of Society | C4: Location | D4: Deal Type | E4: Location Pin | G4: Plot size (sq.m.) | H4: FSI Potential | I4: Regulation Proposed | J4: Development Potential (sq.m.) | K4: Rehab Area (sq.m.) | L4: Sale Area (sq.m.) | M4: Sale Rate Considered (psf) | N4: Topline (in Crores)
B5: Sumer Nagar | C5: Borivali | D5: Society Redevelopment | E5: Maps | G5: 12662 | H5: 5.4 | I5: 33(9) | J5: 68375 | K5: 31810 | L5: 36569 | M5: 35000 | N5: 1330
B6: Khajuria | C6: Kandivali West | D6: Society Redevelopment | E6: Maps | G6: 11895.33 | H6: 5.4 | I6: 30(A) + 33(20B) + 17 | J6: 58298.994 | K6: 11567.197 | L6: 45528.808 | M6: 27000 | N6: 1200
B7: Ambedkar Nagar CHSL | C7: Worli | D7: Society Redevelopment | E7: Maps | G7: 9311 | H7: 5.4 | I7: 33(5) | J7: 43212 | K7: 20196 | L7: 23015 | M7: 65000 | N7: 1481
B8: Jasmine & Moonira lodge | C8: Colaba Causeway | D8: JV/JD | E8: Maps | G8: 1270.91 | H8: 5.4 | N8: 336
B9: Rajendra park | C9: Goregoan West | D9: Society Redevelopment | E9: Maps | G9: 6777.82 | H9: 5.4 | N9: 780
B10: Maker Mahal | C10: Bandra West | D10: Outright | E10: Map | G10: 2025.9 | H10: 5.4 | N10: 800
B11: Lokhandwala Cluster | C11: Andheri West | D11: Society Redevelopment | E11: Maps | G11: 16932 | H11: 6.8 | N11: 2722
B12: Mahindra Nagar | C12: Malad East | D12: Society Redevelopment | E12: Maps | G12: 58367 | H12: 5.4 | N12: 3700
B13: New Jal Darshan | C13: Bandra West | D13: Society Redevelopment | E13: Maps | G13: 2053.2 | H13: 4.05 | N13: 290
B14: Nityanand Bagh | C14: Chembur | D14: Society Redevelopment | E14: Maps | G14: 15348 | H14: 5.4 | N14: 1650
B15: Tolaram | C15: Chembur | D15: Society Redevelopment | E15: Maps | G15: 18618 | H15: 5.4 | N15: 2000

Sheet TransIndia - BD
A1: TransIndia BD Tracker
A2: Sr no. | B2: Properties | C2: Location | E2: Plot size (sq.m.) | F2: Product Type | G2: Structure | H2: Investment Size | I2: Promoter Investment | J2: TransIndia Investment | K2: Total Cost | L2: Topline (in Crores) | M2: Remark
A4: 1 | B4: LKO-KNP INDUSTRIAL SPACE | C4: Lucknow | E4: 37,080 sq m | H4: 140
A5: 2 | B5: Usha Villa | C5: Linking Road | E5: 1026 | H5: 135 | K5: 320 | L5: 455
A6: 3 | B6: SS inventory | C6: Space Residence -II | E6: 40,000 sq.ft | H6: 50
A7: 4 | B7: GTB Nagar (TransIndia) | C7: GTB Nagar Sion | E7: 50,000 sq.ft. | H7: 120
A8: 5 | B8: Sugee Inventory | C8: Mahim | D8: 5,284.32 Sq. mtrs. | E8: 97647.09 sq.ft. | H8: 150 | K8: 531 | L8: 751

Sheet Runwal - Sandeep
A1: Runwal Realty
A2: Property Name | B2: Location | C2: Maps | D2: Deal Type | E2: Plot size (sq.m.) | F2: Topline (in Crores) | G2: Comment | H2: Status
A3: Maker Mahal | B3: =VLOOKUP(A3,'Opps combined list'!$C$4:$E$42,2,FALSE) -> Bandra West | C3: Maps | D3: Outright | E3: 2025.9 | F3: 800 | G3: Members divided between redevelopment and outright sale; exploring part outright and part redevelopment offer with Runwal as partner. | H3: P1
A4: Rajendra Park | B4: Goregoan West | C4: Maps | D4: JV/JD | E4: 6777.82 | F4: 780 | G4: EoI received, Follow up meeting for the Extended cluster to be set | H4: P1
A5: Sumer Nagar | B5: =VLOOKUP(A5,'Opps combined list'!$C$4:$E$42,2,FALSE) -> Borivali | C5: Maps | D5: Society Redevelopment | E5: 12662 | F5: 1330 | G5: Queries addressed; Anex likely to be appointed PMC soon, post which survey and document access will follow. | H5: P1
A6: Doodhsagar | B6: Goregaon East | C6: Maps | D6: Society Redevelopment | E6: 19976 | F6: 3180 | G6: Two concept design options proposed; with no regret offer to be submitted by 12/09/25 | H6: P1
A7: Khajuria Nagar | B7: Kandivali West | C7: Maps | D7: Society Redevelopment | E7: 11895.33 | F7: 1200 | G7: Feasibility and EOI shared | H7: P1
A8: Navyug Nagar Forjett | B8: Tardeo | C8: Maps | D8: Society Redevelopment | E8: 4942 | F8: 914 | G8: Tender has been picked up, being evaluated. Last date to submit the tender is 25/09/2025. SGBM for opening the tender has been scheduled for 28/09/2025 | H8: P1
A9: Pandurang Wadi | B9: Goregaon East | C9: Maps | D9: Society Redevelopment | E9: 6888 | F9: 667 | G9: Prima facie on hold due to topline, should be pursued as 3 more societies expected to be added, RFP open to be picked. Last day to sumbit the EoI is 23/09/2025 | H9: On Hold
A10: Ambedkar Nagar, Worli | B10: Worli | C10: Maps | D10: Society Redevelopment | E10: 9311 | F10: 1481 | G10: Dropped | H10: Dropped
A11: Jasmine (JV/JD) | B11: Colaba | C11: Maps | D11: JV/JD | E11: 1270.91 | F11: 336 | G11: Dropped due to a low topline | H11: Dropped
A12: LBS Marg Open Plot | B12: Vikhroli West | C12: Maps | D12: Outright | E12: 3652 | F12: 735 | G12: Dropped - doesn't align with Runwal's acquisition stratergy | H12: Dropped | I12: -
A13: Red Stone | B13: Juhu | C13: Maps | D13: JV/JD | E13: 1392 | F13: 386 | G13: Proposal not available | H13: Dropped
A14: Sagar CHSL | B14: Mahim | C14: Maps | D14: Society Redevelopment | E14: 4299 | F14: 577 | G14: Dropped due to a low topline | H14: Dropped

Sheet Kalpataru
B1: Kalpataru
B2: Property Name | C2: Location | D2: Deal Type | E2: KL SPOC | F2: Plot size (sq.m.) | G2: Topline (in Crores) | H2: Comment | I2: Status | J2: Lastest updated
A3: 1 | B3: Borla | C3: Chembur | D3: Society Redevelopment | E3: Dhruv | F3: 13890.2 | G3: 2693 | H3: KL participated in the RFP process and awaiting an update. | I3: Interested (P1) | J3: Society has opened all documents, official shortlisting communication awaited.
A4: 2 | B4: Shree Ram | C4: Andheri West | D4: Society Redevelopment | E4: Mohit | F4: 13882 | G4: 1101 | H4: KL participated in the RFP process and preparing concept presentation. | I4: Interested (P1) | J4: Concept presentation has been requested to be pushed to 16th & 17th September. Might happen towards the end of September.
A5: 3 | B5: Karnatak | C5: Khar West | D5: Society Redevelopment | E5: Sonu | F5: 5850 | G5: 852 | H5: KL has sent an EoI. | I5: Interested (P3) | J5: Society had Managing Committee elections which have concluded towards the end of August. Anex to liaise and understand the Society's intentions and way forward.
A6: 4 | B6: Anand Nagar | C6: Santacruz East | D6: Society Redevelopment | E6: Pratik | F6: 6213 | G6: 920 | H6: KL has sent an EoI to Agrawals and first meeting has taken place. | I6: Interested (P1) | J6: KL is in the process of clearing certain liaisoning and constructability related queries and to revert ASAP.
A7: 5 | B7: Powai Open Land | C7: Powai | D7: JV/JD | E7: Pratik | F7: 33365 | G7: 6557 | H7: KL interested due to size and location. | I7: Interested (P3) | J7: Evaluation ongoing and slow as of now.
A8: 6 | B8: LBS Marg Open Plot | C8: Vikhroli West | D8: Outright | E8: Pratik | F8: 3652 | G8: 735 | H8: KL has evaluated and dropped this opportunity. | I8: Dropped | J8: -
A9: 7 | B9: Navyug Nagar | C9: Malabar Hills | D9: Society Redevelopment | E9: Pratik | F9: 4942 | G9: 914 | H9: KL has evaluated and to pick up the tender document. | I9: Interested (P2) | J9: 1st Sept being last day for tender pick up, to understand status.
A10: 8 | B10: GTB Nagar | C10: Sion | D10: DM/JV/JD | E10: Pratik | F10: 20681 | I10: Dropped | J10: -
A11: 9 | B11: RLDA | C11: Mahalaxmi | D11: JV/JD | E11: Mitesh Sir | F11: 10801 | G11: - | H11: All 4 site location options have been sent to Mitesh Sir. | I11: Priotity 1 | J11: To understand the interest in the bidding.
A12: 10 | B12: Khajuria Nagar | C12: Kandivali West | D12: Society Redevelopment | E12: Pratik | F12: 11895.33 | G12: 1200 | H12: KL has issued an EoI to the Societies and landowners. | I12: Interested (P2) | J12: Societies and landowner family to undertake joint discussion with Anex and accordingly next steps to be communicated to KL
